Workbook

Sheet Instructions
A1: Blind human audit — 805 inverse-discordant records
A2: Reviewer: Alberto Zambudio-Munuera | Version: 18 October 2026 | Complete independently before reconciliation
A4: Purpose and blinding
A5: This workbook contains every non-priority record in the inverse discordant pattern: Claude INCLUDE, Codex EXCLUDE, and Grok UNCERTAIN or EXCLUDE (n=805). Previous AI votes and rationales have been removed from view.
A6: Review all rows independently. Do not compare decisions with the other reviewer until both workbooks are complete. The row order was randomized with fixed seed 20261018 and is identical in both reviewer files.
A7: This is title/abstract screening. If eligibility cannot be ruled out from the available information, choose INCLUDE or UNCERTAIN; both trigger retrieval. A missing abstract is not, by itself, a reason to exclude.
A9: Include or retain for full text when
A10: Population: adults with suspected or confirmed prostate cancer, bladder or upper-tract urothelial carcinoma, renal mass, or kidney cancer.
A11: Intervention: AI, machine learning, deep learning, computer vision, natural-language processing, or an algorithmic prediction system contributes to a patient-level or clinical care-pathway task.
A12: Design: randomized comparison; prospective clinical evaluation; prospective or contemporaneous implementation; or a prespecified locked-model evaluation using material from a completed randomized trial.
A13: Outcomes: clinical performance, decisions, workflow, implementation, safety, resources, patient experience, or patient outcomes. At screening, retain uncertainty rather than infer absence.
A15: Exclude only when clearly ineligible
... A21: Enter reviewer_decision, primary_reason when excluded, notes when helpful, and review_date. The Action column is calculated automatically. The control sheet must show 805 reviewed and zero missing exclusion reasons before reconciliation.

Sheet Screening
A1: Blind screening decisions — inverse discordant pattern (n=805)
A2: Yellow columns are reviewer inputs. INCLUDE and UNCERTAIN both advance to retrieval.
A3: audit_order | B3: record_id | C3: year | D3: title | E3: abstract | F3: journal | G3: record_type | H3: abstract_available | I3: reviewer_decision | J3: primary_reason | K3: notes | L3: review_date | M3: action
A4: 1 | B4: LIB-05440 | C4: 2024 | D4: 18F-DCFPyL PET/MRI Radiomics for Intraprostatic Prostate Cancer Detection and Metastases Prediction Using Whole-Gland Segmentation | E4: Introduction: To evaluate the diagnostic performance of combined 18F-DCFPyL PET/MRI whole-gland-derived radiomics for detecting clinically significant (cs) prostate cancer (PCa) (ISUP GG≥2) and predicting nodal and distant metastases in therapy-naïve patients. Methods: This ethics review board-approved, retrospective analysis of two prospective clinical trials included 103 treatment-naïve men who had confirmed or suspected PCa. Recruited patients had either suspicion of PCa and negative systematic biopsies or clinically discordant low-risk PCa (n=20), patients being considered for focal therapy (n=31) or patients with unfavourable intermediate or high-risk PCa (n=52). All patients were enrolled between 2017 and 2020 and underwent 18F-DCFPyL PET/MRI. Radiomic feature analysis of PET/MRI was obtained using commercial software via the quantitation of various radionics features based on the spatial arrangement and variation of pixel intensities within a defined volume of interest. Whole-prostate segmentations were performed on each modality separately. On the MRI, whole-gland T2-weighted sequence and whole-gland apparent diffusion coefficient (ADC) map were evaluated. PET volumes of interest (VOI) were defined based on (a) background threshold, (b) peak threshold, (c) threshold at 40%, and (d) threshold at 70% of the SUVmax. Since a thresholding method was not available for the MRI component (T2, ADC), the contours for the MRI-derived VOI were performed manually (by an expert specialist in prostate MRI) in a slice-by-slice fashion to cover the entire prostate. The radiomics features, including overall 307 different features, were extracted from the segmented volumes in accordance with the image biomarker standardization initiative (IBSI) guidelines. The reference standard for suspicious prostatic lesions was histopathology (prostate biopsy) in all patients. The highest reported ISUP GG was taken into account for each prostate gland. For nodal and distant metastatic assessment, a composite standard of reference was applied for all lesions identified on conventional imaging (CT and bone scan ± mpMRI) or PET and included histopathology, correlative imaging, and clinical/biochemical follow-up. Univariate logistic regression was done to evaluate potential predictors across all calculated features. A predictive modelling approach using multivariable logistic regression with internal cross-validation was performed to calculate estimates and evaluate model performance. Results: A total of 103 patients (mean age=65; mean PSA=23.4) were evaluated. csPCa was confirmed in 89 (86%) patients, four patients had ISUP GG1, and 10 patients were negative for malignancy. Multiple models were built to predict the whole-gland ISUP GG, including clinical (Age and PSA), T2w (MRI-only; including only NGLDM Busyness), 18F-DCFPyL PET (PET-only; including only NGLDM Busyness), clinical+T2w, clinical+PET, T2w+PET (hybrid), and clinical+T2w+PET (full model). The imaging-based hybrid model (T2w+PET) provided the highest AUC (0.89) for the prediction of csPCa. No statistically significant PET or MRI radiomic feature was found for N-stage prediction. For M staging, the T2w whole-gland radiomic was found to be the best predictive model (AUC=0.94). Conclusions: Hybrid PET/MRI radiomics (whole-gland T2w+PET) was the best-performing model to predict csPCA, outperforming the clinical model. This indicates a complementary value of the hybrid PET/MRI model for noninvasive csPCa detection. Additionally, T2w whole-gland radiomics was able to predict distant metastases in this cohort. | F4: J. Nucl. Med. | G4: JOUR; Conference Abstract | H4: YES | I4: EXCLUDE | J4: Ineligible publication type | K4: CONFERENCE_ABSTRACT | L4: 46313 | M4: =IF(OR(I4="INCLUDE",I4="UNCERTAIN"),"RETRIEVE",IF(I4="EXCLUDE","EXCLUDE",""))
A5: 2 | B5: LIB-03469 | C5: 2026 | D5: Artificial-intelligence models vs. radiologists in the detection of clinically significant prostate cancer on mpMRI: a meta-analysis. | E5: OBJECTIVE: Multiparametric magnetic resonance imaging (mpMRI) detects clinically significant prostate cancer (csPCa, Gleason Grade Group ≥ 2) with high sensitivity but limited specificity and inter-reader variability. Artificial intelligence (AI), particularly convolutional neural networks (CNNs) and deep learning, may improve diagnostic consistency and accuracy. This meta-analysis compares AI systems and experienced radiologists in detecting csPCa using mpMRI. METHODS: We performed a systematic review and meta-analysis of English-language non-RCT studies. PubMed, Embase, and Cochrane databases were searched up to May 2025, yielding 855 studies. Only studies comparing CNN-based or deep-learning AI models to radiologists were included. Pooled sensitivity, specificity, diagnostic odds ratio (DOR), and area under the receiver operating curve (AUC) were calculated using a bivariate random-effects model. RESULTS: Ten studies with 2586 patients were analyzed. AI systems showed pooled sensitivity of 0.90 (95% CI 0.84-0.94) and specificity of 0.69 (95% CI 0.45-0.85). Radiologists had a sensitivity of 0.89 (95% CI 0.82-0.94) and a specificity of 0.60 (95% CI 0.43-0.75). DOR was 17.54 (95% CI 9.34-32.94) for AI and 12.35 (95% CI 4.96-30.76) for radiologists. Summary receiver operating characteristic (SROC) curves indicated similar diagnostic accuracy, with AI slightly outperforming radiologists (AUC 0.88 vs. 0.85). CONCLUSION: AI systems perform comparably to radiologists in detecting csPCa on mpMRI, with a potential edge in specificity, though confidence intervals overlapped. High heterogeneity and the retrospective nature of all included studies limit reliability, necessitating prospective validation. AI could serve as an adjunct in prostate cancer diagnosis, potentially improving precision and reducing unnecessary biopsies with further model refinement. KEY POINTS: Question Interpretation of mpMRI for clinically significant prostate cancer varies among radiologists, affecting diagnostic consistency. Findings Meta-analysis shows AI has comparable sensitivity and potentially superior specificity to radiologists in detecting significant prostate cancer on mpMRI, though confidence intervals overlapped. Clinical relevance AI has the potential to enhance diagnostic accuracy, reduce unnecessary biopsies, and improve consistency in prostate cancer detection, thereby supporting more reliable and standardized imaging assessments across centers. | F5: European radiology | G5: Journal Article; Meta-Analysis; Systematic Review; Comparative Study | H5: YES | I5: EXCLUDE | J5: Ineligible publication type | K5: NON_PRIMARY_PUBLICATION | L5: 46313 | M5: =IF(OR(I5="INCLUDE",I5="UNCERTAIN"),"RETRIEVE",IF(I5="EXCLUDE","EXCLUDE",""))
A6: 3 | B6: LIB-06805 | C6: 2019 | D6: Serial T2-Weighted Magnetic Resonance Images Acquired on a 1.5 Tesla Magnetic Resonance Linear Accelerator Reveal Radiomic Feature Variation in Organs at Risk: An Exploratory Analysis of Novel Metrics of Tissue Response in Prostate Cancer. | E6: "Delta-radiomics" investigates variations in quantitative image metrics over time and can yield important clinical information. We hypothesized that in patients undergoing active radiation therapy (RT) for prostate cancer (PCa), there would exist observable variation in the quantitative metrics that describe the T2-weighted (T2W) intensity histogram in the prostate and surrounding organs at risk (OAR) over time. We investigated the feasibility of acquisition and subsequent analysis of the delta-radiomic profiles of these regions of interest (ROI) in serial T2W magnetic resonance (MR) images obtained on a 1.5 Tesla (T) Magnetic Resonance Linear Accelerator (MRL). Principally, we sought to illustrate the significance of longitudinal radiomic data acquisition for tissue response monitoring and provide a framework for future hypothesis driven research. Patients with PCa undergoing treatment with RT were compiled from an ongoing prospective observational imaging trial using a 1.5 T MRL (NCT30500081). Contiguous axial slices of prostate parenchyma were contoured and temporally normalized to sections of Sartorius muscle which served as a control. Similarly, contiguous sections of rectal and bladder wall adjacent to the prostate were contoured and temporally normalized to regions of these organs further removed from the planning target volume (PTV). First order statistical descriptors of the T2W intensity histogram were extracted and evaluated for changes over time using linear mixed effects regression modeling and post-hoc contrasts. Benjamini-Hochberg corrections were employed to reduce the effects of multiple testing and control for the false discovery rate (FDR). Four patients with a median age of 69 comprised this exploratory cohort. One patient had low-risk disease, two had intermediate (one favorable, one unfavorable), and one had high risk disease. Three out of four patients underwent definitive radiation to 75.6 Gray (Gy) in 42 fractions and one received hypofractionated therapy to a total dose of 70 Gy over 28 fractions, and all received treatment on a conventional linear accelerator. The most significant acute toxicity event was grade 2 GU dysfunction observed in two patients. Follow up ranged from 1 month to 10 months post treatment, and no long-term complications were reported in patients who completed treatment at least one month prior. Bladder wall adjacent to the prostate demonstrated significant variation in the mean and median metric values after the first week of treatment. In addition, rectal wall adjacent to the prostate exhibited significant variation in the mean, median, and standard deviation metric values by the second week of treatment. No significant variation in any radiomic feature was observed in the Sartorius control. This exploratory study is one of the earliest examining the delta-radiomic characteristics of the T2W intensity histogram in OAR extracted from images acquired on a 1.5 T MRL in patients actively being treated with RT for PCa. We demonstrated a feasible approach to longitudinal radiomic data acquisition providing limitless opportunity for future research. Analysis of the delta-radiomic profiles in OAR revealed significant variation in metrics after only one week of RT in bladder and rectal wall adjacent to the prostate. These findings must be further investigated and validated with expanded data sets with long-term follow up and correlation to clinical outcomes including toxicity and tumor control. | F6: Cureus | G6: Journal Article | H6: YES | I6: EXCLUDE | J6: No eligible AI/ML system | K6: NO_RELEVANT_AI | L6: 46313 | M6: =IF(OR(I6="INCLUDE",I6="UNCERTAIN"),"RETRIEVE",IF(I6="EXCLUDE","EXCLUDE",""))
A7: 4 | B7: LIB-05517 | C7: 2025 | D7: Comparative outcomes and prognosis in patients with ureteral upper tract urothelial carcinoma undergoing segmental ureterectomy versus radical nephroureterectomy: a multicenter cohort study. | E7: BACKGROUND: Although radical nephroureterectomy (RNU) with bladder cuff excision remains the gold standard treatment for upper tract urothelial carcinoma (UTUC), segmental ureterectomy (SU) may offer a nephron-sparing alternative. Studies comparing oncologic outcomes and renal functional outcomes between SU and RNU have yielded controversial, often conflicting results. Furthermore, investigations specifically involving ureteral UTUC patients in northern China are scarce. METHODS: We retrospectively enrolled 546 ureteral urothelial carcinoma patients (282 SU and 264 RNU cases) from three hospitals between October 2003 and September 2024 to assess overall survival (OS) and intravesical recurrence-free survival (IV-RFS) as oncologic outcomes, and to evaluate renal functional outcomes (preoperative, postoperative [2-month] and delta change in estimated glomerular filtration rate [eGFR] and serum creatinine [Scr]). The prognostic impact of surgical approach and clinicopathological variables were evaluated using Kaplan-Meier analysis with log-rank tests and Cox regression models. Significant predictors were incorporated into a validated nomogram for personalized 3-, 4-, and 5-year OS and IV-RFS probability estimation. Furthermore, eight machine learning algorithms (Lasso Cox, random survival forest [RSF], CoxBoost, generalized boosted regression modeling [GBM], support vector machine [Survival-SVM], eXtreme Gradient Boosting [XGBoost], supervised principal components [SuperPC], and partial least squares regression for Cox [plsRcox]) were implemented for OS and IV-RFS prediction modeling. Finally, we quantitatively pooled our cohort data with literature evidence retrieved from major databases (PubMed, Cochrane, Embase, Web of Science) up to 21 May 2025, to compare survival and renal function outcomes between the two procedures using Stata 14.0. Subgroup assessments and leave-one-out sensitivity analyses were performed to address potential confounding factors related to heterogeneity. RESULTS: Firstly, the multicenter retrospective cohort study revealed that SU was associated with reduced IV-RFS and was identified as a significant independent predictor of IV-RFS (HR = 1.48; P = 0.02). Meanwhile, there was no significant difference in OS between SU and RNU. Algorithm comparison confirmed optimal discriminative performance for IV-RFS (3-year AUC: 0.771, 4-year: 0.758, 5-year: 0.761) and OS (3-year AUC: 0.739, 4-year: 0.726, 5-year: 0.710). Decision curve analysis demonstrated the excellent clinical applicability of the nomograms for OS and IV-RFS, which enhanced model precision and clinical utility. Furthermore, in the meta-analysis, 21 studies including 31 293 patients were selected for inclusion, spanning publication years from 2010 to 2025. Regarding survival outcomes, although no statistically significant differences were observed in OS risk ( P = 0.696), CSS risk ( P = 0.765), or RFS ( P = 0.072) between patients receiving SU and those undergoing RNU, SU was associated with lower IV-RFS compared to RNU (HR = 1.21, P = 0.019). Subgroup analysis stratified by geographic region revealed significantly reduced OS with SU versus RNU in European cohorts (HR = 1.24, P = 0.001). Concerning renal functional outcomes, the SU group demonstrated significantly higher postoperative eGFR (WMD, 14.16 mL/min; P < 0.001) and greater delta change in eGFR (WMD, 11.78 mL/min; P < 0.001). CONCLUSION: SU achieves cancer-specific and overall survival comparable to RNU, even in high-grade ureteral UTUC, while significantly improving postoperative renal function. However, it necessitates multidisciplinary management of intravesical recurrence risk. Validation of molecular predictors and prospective trials in advanced disease are essential to further expand and validate the therapeutic landscape of SU. | F7: International journal of surgery (London, England) | G7: Journal Article; Multicenter Study; Comparative Study | H7: YES | I7: EXCLUDE | J7: No eligible AI/ML system | K7: NO_RELEVANT_AI | L7: 46313 | M7: =IF(OR(I7="INCLUDE",I7="UNCERTAIN"),"RETRIEVE",IF(I7="EXCLUDE","EXCLUDE",""))
A8: 5 | B8: LIB-01411 | C8: 2023 | D8: The efficacy of red channel enhanced images for AI segmentation of bladder tumors in Cystoscopic | E8: Introduction & Objectives: Bladder tumors have high intravesical recurrence rate after transurethral resection of the bladder tumor (TURBT). Especially, overlooking and incompletely resecting tumors causes early intravesical recurrences. White light imaging (WLI) is the gold standard method, however it sometimes overlooked tumors about 10-20%. Although Narrow-band imaging and photodynamic diagnosis have improved the detection sensitivities, those accuracies are less objective and poor reproducible. Recently, artificial intelligence (AI) has been applying in diagnostic imaging. Segmentation is a commonly used AI method to present the shape of the object, and has possibility to correctly display the bladder tumors. In general, many cystoscpic images must be collected to create highly accurate AI; However, collecting the enormous images from only one institution is arduous task. To solve this problem, image processing has possibility to improve segmentation accuracies. In this study, we implemented image processing system that enhanced red color channel of cystoscopic images, and evaluated its efficacy in AI segmentation comparing to original cystoscopic images. Materials & Methods: We retrospectively collected cystoscopic images by converting TURBT videos, and divided those images into training and testing data. We constructed a segmentation system based on U-Net and implemented the image processing system to automatically create red channel enhanced image (RCEI). We conducted two AI training; one was the trained by only original cystoscopic images and another was the trained by only RCEI, and compared the two segmentation accuracies. As the evaluation metrics, we calculated IoU that represents the overlap area between the bladder tumors in the ground truth images and the AI segmentation maps. We also calculated pixel-wise sensitivity (PWSe), pixel-wise specificity (PWSp) and pixel-wise positive predictive value (PWPPV), representing the AI diagnostic accuracy per pixel. Results: We obtained 1,790 cystoscopic images from 120 patients. The T-stage of tumors are follows; 70, Ta; 22, T1; 21, T2; 9 carcinoma in situ, respectively. The IoU, PWSe, and PWPPV in RCEI were 77.0%, 88.0%, and 86.5%, which had improved 3.7%, 3.3%, and 1.3% of the AI trained by only original cystoscopic images, respectively. Conclusions: Our proposed image processing system could detect and display more bladder tumors compared with conventional cystoscopic images. Based on this system, we will try to create real time detecting-aid segmentation system. [Figure presented] | F8: Eur. Urol. | G8: JOUR; Conference Abstract | H8: YES | I8: EXCLUDE | J8: Ineligible publication type | K8: CONFERENCE_ABSTRACT | L8: 46313 | M8: =IF(OR(I8="INCLUDE",I8="UNCERTAIN"),"RETRIEVE",IF(I8="EXCLUDE","EXCLUDE",""))
A9: 6 | B9: LIB-00259 | C9: 2023 | D9: CONFIDENT-trial protocol: a pragmatic template for clinical implementation of artificial intelligence assistance in pathology. | E9: INTRODUCTION: Artificial intelligence (AI) has been on the rise in the field of pathology. Despite promising results in retrospective studies, and several CE-IVD certified algorithms on the market, prospective clinical implementation studies of AI have yet to be performed, to the best of our knowledge. In this trial, we will explore the benefits of an AI-assisted pathology workflow, while maintaining diagnostic safety standards. METHODS AND ANALYSIS: This is a Standard Protocol Items: Recommendations for Interventional Trials-Artificial Intelligence compliant single-centre, controlled clinical trial, in a fully digital academic pathology laboratory. We will prospectively include prostate cancer patients who undergo prostate needle biopsies (CONFIDENT-P) and breast cancer patients who undergo a sentinel node procedure (CONFIDENT-B) in the University Medical Centre Utrecht. For both the CONFIDENT-B and CONFIDENT-P trials, the specific pathology specimens will be pseudo-randomised to be assessed by a pathologist with or without AI assistance in a pragmatic (bi-)weekly sequential design. In the intervention group, pathologists will assess whole slide images (WSI) of the standard hematoxylin and eosin (H&E)-stained sections assisted by the output of the algorithm. In the control group, pathologists will assess H&E WSI according to the current clinical workflow. If no tumour cells are identified or when the pathologist is in doubt, immunohistochemistry (IHC) staining will be performed. At least 80 patients in the CONFIDENT-P and 180 patients in the CONFIDENT-B trial will need to be enrolled to detect superiority, allocated as 1:1. Primary endpoint for both trials is the number of saved resources of IHC staining procedures for detecting tumour cells, since this will clarify tangible cost savings that will support the business case for AI. ETHICS AND DISSEMINATION: The ethics committee (MREC NedMec) waived the need of official ethical approval, since participants are not subjected to procedures nor are they required to follow rules. Results of both trials (CONFIDENT-B and CONFIDENT-P) will be published in scientific peer-reviewed journals. | F9: BMJ open | G9: Journal Article; Research Support, Non-U.S. Gov't | H9: YES | I9: EXCLUDE | J9: Protocol/no results | K9: PROTOCOL_NO_RESULTS | L9: 46313 | M9: =IF(OR(I9="INCLUDE",I9="UNCERTAIN"),"RETRIEVE",IF(I9="EXCLUDE","EXCLUDE",""))
A10: 7 | B10: LIB-03896 | C10: 2026 | D10: Analysis of genomic and clinical predictors of overall survival and PSA response: Results from the PRECISION registry. | E10: Background: Outcomes in advanced prostate cancer vary substantially according to clinical and genomic characteristics among patients with metastatic castration-resistant prostate cancer (mCRPC). We sought to identify predictors of overall survival (OS) and prostate-specific antigen (PSA) response using data from the PRECISION real-world registry of mCRPC patients treated with poly(ADP-ribose) polymerase inhibitors (PARPi). Methods: Patient-level data from five centers (Dana Farber Cancer Institute, Thomas Jefferson University, University of British Colombia, University of Washington, Yale University) were aggregated, including demographics, clinical characteristics, genomic alterations, treatments, and clinical outcomes. OS was defined as the time from the first date of PARPi treatment to death or the last date the patient was known to be alive. PSA response was defined as a confirmed ≥50% decline from the PSA level measured closest to the start of PARPi treatment. Ten candidate variables per endpoint were selected via a random forest-based feature selection. Cox models stratified by study were used for OS, and logistic regression models with study included as an additional covariate were used for PSA response. Similarly, non-BRCA mutation status was defined as the presence of any observed mutation in genes other than BRCA, including ATM, CHEK2, MSH2, PALB2, BRIP1, and BARD1. Results: The combined dataset included n = 327 patients, with heterogeneity in baseline characteristics and treatments across studies. The prevalence of BRCA (BRCA1 or BRCA2) and non BRCA mutations was 39% and 37% respectively. Median OS for patients with BRCA mutations was 21 months (95% CI:16–28), compared with 15 months (95% CI: 14–18) for those without BRCA mutations. No difference in median OS was observed between patients with and without non-BRCA mutations: 16 months (95%CI: 14-22) and 17 months (15-21), respectively. Cox models identified age, N stage, PSMA–lutetium therapy, PARPi use within a clinical trial, prior taxane treatment (docetaxel or cabazitaxel), and BRCA as important predictors of OS. The corresponding hazard ratios with 95% confidence intervals are shown in the table below. Conclusions: These results from real-world data highlight the importance of incorporating genomic information and treatment-specific variables when predicting outcomes in advanced prostate cancer and demonstrate the utility of multi-study integrative analyses. (Table Presented.) | F10: ASCO MEETING ABSTRACTS | G10: JOUR; Conference Abstract | H10: YES | I10: EXCLUDE | J10: Ineligible publication type | K10: CONFERENCE_ABSTRACT | L10: 46313 | M10: =IF(OR(I10="INCLUDE",I10="UNCERTAIN"),"RETRIEVE",IF(I10="EXCLUDE","EXCLUDE",""))
A11: 8 | B11: LIB-04470 | C11: 2018 | D11: Machine learning-based lesion detection via quantitative high frequency ultrasound for prostate-cancer imaging using a novel high resolution micro-ultrasound platform | E11: INTRODUCTION AND OBJECTIVES: Currently, transrectal ultrasound (TRUS) guided biopsies is the only method for definitive diagnosis of prostate cancer. Studies by our group suggest that quantitative ultrasound (QUS) using machine learning-based lesion detection via high resolution micro-ultrasound could provide a more-sensitive, automated mechanism of identifying and targeting biopsies at cancersuspicious regions in the prostate. METHODS: Our previous studies utilized ultrasound signals at typical clinical frequencies, i.e., in the 6-MHz range. In our current study, a novel, 29-MHz, fine-resolution, micro-ultrasound instrument (ExactVuTM micro-ultrasound, Exact Imaging, Markham, Canada) was used to acquire RF data from 163 patients directly before 12-core biopsy (1,956 cores total). These retrospective data are a subset of data acquired in a multisite, 1,676-patient, randomized, clinical trial (clinicaltrials.gov NCT02079025). Machine learning-based lesion detection incorporated the following spectral-QUS features: effective scatter diameter (ESD), effective acoustic concentration (EAC), midband (M), intercept (I) and slope (S) as well as envelope statistics using a Nakagami distribution. The values of these features were calculated and used to train linear discriminant classifiers (LDCs) and support-vector machines (SVMs). Classifier performance was assessed using area-under-the-curve (AUC) values obtained from receiver operating characteristic (ROC) analyses with 10-fold cross validation. RESULTS: A combination of ESD and EAC parameters resulted in an AUC value of 0.75 using an LDC. When the PSA value was added as a feature, the AUC increased to 0.79. The best classification performance was obtained using an LDC by combining envelope statistics, PSA, ESD and EAC, which resulted in an AUC of 0.81. Using an SVM did not improve the classification significantly (i.e., best classifier AUC~0.75). In a separate study of the imaging capabilities of the ExactVuTM instrument, B-mode-based scoring and evaluation of lesions achieved an AUC of 0.74 for higher GS values (Gleason Sum > 7) for images interpreted by an expert. CONCLUSIONS: The AUC value of 0.81 achieved in the current study provides an encouraging basis for developing a new, entirely objective, automated method of assessing prostate-cancer risk and depicting suspicious regions in fine-resolution, real-time, micro-ultrasound images. The study results demonstrate that QUS-based imaging methods have great promise for reliably targeting prostate biopsies, planning and delivering focal treatment of prostate cancers, and monitoring treated or watched prostate cancers. | F11: J. Urol. | G11: JOUR; Conference Abstract | H11: YES | I11: EXCLUDE | J11: Ineligible publication type | K11: CONFERENCE_ABSTRACT | L11: 46313 | M11: =IF(OR(I11="INCLUDE",I11="UNCERTAIN"),"RETRIEVE",IF(I11="EXCLUDE","EXCLUDE",""))
A12: 9 | B12: LIB-06190 | C12: 2025 | D12: Artificial Intelligence Across the Prostate Cancer Pathway: Screening, Imaging, Pathology, and Biomarkers. | E12: Artificial intelligence (AI) has made great changes to prostate cancer screening and early detection across biomarkers, imaging, and pathology. On micro-ultrasound (micro-US), AI improves discrimination and raises specificity at comparable sensitivity versus clinical models, while multimodal magnetic resonance imaging-transrectal US (MRI-TRUS) AI achieves higher specificity at matched sensitivity. Liquid-biopsy programs combine fragmentomics with ctDNA and cell-free mRNA interpreted by AI, enabling noninvasive risk stratification and clinical feasibility. In imaging, AI for MRI matches or exceeds expert radiologists in large reader studies and MRI benchmarks; commercial tools show robust patient- and lesion-level performance. Quantitative pipelines (e.g., automated tissue-composition metrics) aid equivocal Prostate Imaging-Reporting and Data System (PI-RADS 3) lesions with PSA density, and AI-derived intraprostatic tumor volume offers independent prognostic value. Multimodal fusion of MRI with TRUS boosts detection, and automated prostate-specific membrane antigen (PSMA) PET/CT algorithms quantify tumor burden and support longitudinal response tracking. In pathology, clinical-grade AI automates cancer detection and Gleason grading, cutting reading time, ancillary tests, and second-opinion requests, while supporting integrative prognostic models. Downstream, AI accelerates radiotherapy planning, guides focal therapies and surgical margins, personalizes systemic therapy, and enables early post-treatment monitoring. Translation still requires rigorous, prospective, multi-site validation. | F12: Cureus | G12: Journal Article; Review | H12: YES | I12: EXCLUDE | J12: Ineligible publication type | K12: NON_PRIMARY_PUBLICATION | L12: 46313 | M12: =IF(OR(I12="INCLUDE",I12="UNCERTAIN"),"RETRIEVE",IF(I12="EXCLUDE","EXCLUDE",""))
A13: 10 | B13: LIB-00667 | C13: 2020 | D13: Validation and implementation of a mobile app decision support system for quality assurance of tumor boards. Analyzing the concordance rates for prostate cancer at a multidisciplinary tumor board of a tertiary referral centre | E13: Introduction & Objectives: Certified Cancer Centers are instructed to present 100% of all cases at multidisciplinary tumor boards (MTD). Discussion of standard cases limits the time of more demanding cases. A validated expert-curated decision support system (DSS) could avoid the discussion of standard cases in MTD and provide sufficient time for demanding cases. Materials & Methods: In order to verify the quality of each single tumor board decision, we first developed a partially algorithm-driven DSS mobile application to provide evidence-based recommendations for first-line therapy of common urological cancers. In a second step, concordance rate was determined by comparing treatment recommendations given by DSS and MTD. Data of 1924 patients with prostate cancer being discussed in the MTD of the urological department of the University Hospital of Cologne between 2014 and 2018 have been included for evaluation. Patient characteristics included age, disease stage, Gleason Score, PSA and previous therapies. All cases were then answered using the DSS mobile application. The results of both MTD and DSS were included into an identical layout style for reviewer evaluation. All pairs of answers were compared by two independent, blinded reviewers and were categorized into four groups of concordance level: Identical decision (ID), correct alternative decision (CAD), different decision (DD), no decision (ND). Results: Overall concordance rate was 99.6%, including 94.1% ID and 5.5% CAD. Stage specific concordance rates were 99.6% (stage I), 99.8% (stage II), 100% (stage III), and 99.3% (stage IV). Quality of concordance were independent of age, risk profile or line of treatment. Conclusions: Our expert-curated DSS provides nearly 100% concordance with a specialized MTD. Despite these good results and superiority to other DSS reported so far, we aim for a next generation solution with mutual quality control on both sides: human being and machine and vice versa. To assure quality and to fulfill the expectation to become a standard tool for validation and quality assurance of multidisciplinary tumor boards in general, we currently initiate a prospective multicenter board cross-validation trial. | F13: Eu. Uro. Op. Sci | G13: JOUR; Conference Abstract | H13: YES | I13: EXCLUDE | J13: Ineligible publication type | K13: CONFERENCE_ABSTRACT | L13: 46313 | M13: =IF(OR(I13="INCLUDE",I13="UNCERTAIN"),"RETRIEVE",IF(I13="EXCLUDE","EXCLUDE",""))
A14: 11 | B14: LIB-04638 | C14: 2019 | D14: Prediction of metastatic castrate-resistant prostate cancer response to abiraterone or enzalutamide by a baseline blood-based CTC gene expression signature | E14: Background: Prostate cancer is the most common cancer in men in the U.S., with 30% 5-year overall survival (OS) for patients (pts) with metastases. To take a precision medicine approach to the management of metastatic castrate-resistant prostate cancer (mCRPC), we developed a blood circulating tumor cell (CTC)-based test to identify mCRPC pts most likely to benefit from abiraterone (abi) or enzalutamide (enza). Methods: In this multi-institution prospective study, men with mCRPC were enrolled prior to starting abi (1,000 mg/d plus prednisone 10 mg/d) or enza (160 mg/d). At baseline (BL), 12 w, and progression, blood samples were collected for CellSearch-based CTC enumeration and qPCR-based gene expression analysis. Results: 69 pts (median age 68 y [50-82]) received abi (n = 25) or enza (n = 44) and had evaluable blood samples. Consistent with prior publications, among 43 pts with BL CTC > 0, clearance of detectable CTCs (BL CTCs > 0 and 12 w CTCs = 0), was achieved in 24 patients (55.8%), and was associated with greater median OS (31 mo vs. 18 mo, log-rank p = 0.03). The 43 pts with BL CTC > 0 were then randomly divided into training (n = 31) and validation (n = 12) sets. Baseline gene expression data for the training set was used to develop a model to predict CTC clearance, starting with a panel of 141 expressed genes/isoforms including those associated with prostate cancer. Of the models tested, random forest yielded the best performance, with respective training and validation set sensitivity of 0.7 and 1, specificity 0.75 and 0.71, AUC 0.88 and 0.91. Top genes identified include those previously associated with disease - HOXB13, ESRP2, KLK3, GRHL2, andKRT19, among others. Conclusions: A gene expression signature from a baseline blood sample with CellSearch-enriched CTCs can predict clearance of detectable CTCs in response to abi/enza with high AUC and may give insight into molecular mechanisms of response. A prospective study with a larger number of patients will be required to further validate our findings. Ultimately, this blood test has the potential to select the patients most likely to benefit from second-generation antiandrogen vs. non-hormonal systemic treatment. | F14: J. Clin. Oncol. | G14: JOUR; Conference Abstract | H14: YES | I14: EXCLUDE | J14: Ineligible publication type | K14: CONFERENCE_ABSTRACT | L14: 46313 | M14: =IF(OR(I14="INCLUDE",I14="UNCERTAIN"),"RETRIEVE",IF(I14="EXCLUDE","EXCLUDE",""))
A15: 12 | B15: LIB-02978 | C15: 2025 | D15: AI-driven and Traditional Radiomic Model for Predicting Muscle Invasion in Bladder Cancer via Multi-parametric Imaging: A Systematic Review and Meta-analysis. | E15: RATIONALE AND OBJECTIVES: This study systematically evaluates the diagnostic performance of artificial intelligence (AI)-driven and conventional radiomics models in detecting muscle-invasive bladder cancer (MIBC) through meta-analytical approaches. Furthermore, it investigates their potential synergistic value with the Vesical Imaging-Reporting and Data System (VI-RADS) and assesses clinical translation prospects. METHODS: This study adhered to the Preferred Reporting Items for Systematic Reviews and Meta-Analyses (PRISMA) guidelines. We conducted a comprehensive systematic search of PubMed, Web of Science, Embase, and Cochrane Library databases up to May 13, 2025, and manually screened the references of included studies. The quality and risk of bias of the selected studies were assessed using the Quality Assessment of Diagnostic Accuracy Studies 2 (QUADAS-2) and Radiomics Quality Score (RQS) tools. We pooled the area under the curve (AUC), sensitivity, specificity, positive likelihood ratio (PLR), negative likelihood ratio (NLR), diagnostic odds ratio (DOR), and their 95% confidence intervals (95% CI). Additionally, meta-regression and subgroup analyses were performed to identify potential sources of heterogeneity. RESULTS: This meta-analysis incorporated 43 studies comprising 9624 patients. The majority of included studies demonstrated low risk of bias, with a mean RQS of 18.89. Pooled analysis yielded an AUC of 0.92 (95% CI: 0.89-0.94). The aggregate sensitivity and specificity were both 0.86 (95% CI: 0.84-0.87), with heterogeneity indices of I² = 43.58 and I² = 72.76, respectively. The PLR was 5.97 (95% CI: 5.28-6.75, I² = 64.04), while the NLR was 0.17 (95% CI: 0.15-0.19, I² = 37.68). The DOR reached 35.57 (95% CI: 29.76-42.51, I² = 99.92). Notably, all included studies exhibited significant heterogeneity (P < 0.1). Meta-regression and subgroup analyses identified several significant sources of heterogeneity, including: study center type (single-center vs. multi-center), sample size (<100 vs. ≥100 patients), dataset classification (training, validation, testing, or ungrouped), imaging modality (computed tomography [CT] vs. magnetic resonance imaging [MRI]), modeling algorithm (deep learning vs. machine learning vs. other), validation methodology (cross-validation vs. cohort validation), segmentation method (manual vs. [semi]automated), regional differences (China vs. other countries), and risk of bias (high vs. low vs. unclear). CONCLUSION: AI-driven and traditional radiomic models have exhibited robust diagnostic performance for MIBC. Nevertheless, substantial heterogeneity across studies necessitates validation through multinational, multicenter prospective cohort studies to establish external validity. | F15: Academic radiology | G15: Journal Article; Meta-Analysis; Systematic Review; Research Support, Non-U.S. Gov't | H15: YES | I15: EXCLUDE | J15: Ineligible publication type | K15: NON_PRIMARY_PUBLICATION | L15: 46313 | M15: =IF(OR(I15="INCLUDE",I15="UNCERTAIN"),"RETRIEVE",IF(I15="EXCLUDE","EXCLUDE",""))
... A48: 45 | B48: LIB-05847 | C48: 2026 | D48: Online adaptive radiotherapy in pelvic and thoracic cancers - comparing toxicities, clinical outcomes and technical parameters between conventional image-guided radiotherapy and online adaptive radiotherapy - the study protocol for the prospective, registry-based cohort study (PRoART). | E48: BACKGROUND: Conventional image-guided radiotherapy (IGRT) typically relies on a computed tomography (CT)-based treatment planning process (planning CT, pCT) performed prior to the start of treatment. During this process, a patient-specific treatment plan is generated, which is then delivered to the patient with a linear accelerator on a daily basis, usually with image guidance to compensate for variations in patient setup. However, daily interfractional anatomical variations in target position, shape, and volume, as well as in surrounding organs at risk (OARs), can only be addressed indirectly by adding safety margins, resulting in larger irradiated volumes and potentially increased toxicity. Online adaptive radiotherapy (oART) is a promising and innovative technique to reduce such margins and, consequently, treatment-related toxicity. It uses daily imaging to generate a "plan of the day" that is aligned with the current patient anatomy, often supported by artificial intelligence (AI), while the patient remains on the treatment couch. Through daily image-guided re-optimization of the radiation treatment (RT) plan on the anatomy of the day, target coverage may also be improved. This approach is particularly attractive in the pelvic region, where high interfractional anatomical variability, for example due to peristalsis or changes in bladder and rectal filling, is frequently observed. METHODS: This prospective registry-based cohort study will include patients with pelvic or thoracic tumors with an indication for RT treated with IGRT or oART using the Varian Ethos™ system. The primary endpoint is defined as a 10% reduction in the rate of acute RT related toxicity (≥Common Terminology Criteria for Adverse Events (CTCAE) II°, v5.0) using oART. Secondary endpoints encompass clinical outcomes including late toxicities, tumor control rates, and patient-reported outcomes (PROs), as well as technical factors such as target volume, coverage, dose to OARs and anatomical variability score. While the cohort study compares IGRT versus oART for primary and secondary clinical endpoints, it also evaluates the real oART scenario against two hypothetical control scenarios for technical endpoints. DISCUSSION: The introduction of oART promises a reduction in toxicities and improved target volume coverage, potentially resulting in enhanced tumor control rates. It is poised to be a pioneering technology in the field of radiation oncology. Given the absence of a direct comparison between IGRT and oART thus far, the prospective registry-based cohort study PRoART aims to address this gap. TRIAL REGISTRATION: Clinical trial number NCT06185062, Clinicaltrials.gov. Registered 12/14/2023. Last update 07/29/2026. | F48: BMC medical imaging | G48: Journal Article; Comparative Study | H48: YES | I48: EXCLUDE | J48: Protocol/no results | K48: PROTOCOL_NO_RESULTS | L48: 46313 | M48: =IF(OR(I48="INCLUDE",I48="UNCERTAIN"),"RETRIEVE",IF(I48="EXCLUDE","EXCLUDE",""))
A49: 46 | B49: LIB-01333 | C49: 2023 | D49: Thin-Slice Prostate MRI Enabled by Deep Learning Image Reconstruction. | E49: OBJECTIVES: Thin-slice prostate MRI might be beneficial for prostate cancer diagnostics. However, prolongation of acquisition time is a major drawback of thin-slice imaging. Therefore, the purpose of this study was to investigate the impact of a thin-slice deep learning accelerated T2-weighted (w) TSE imaging sequence (T2DLR) of the prostate as compared to conventional T2w TSE imaging (T2S). MATERIALS AND METHODS: Thirty patients were included in this prospective study at one university center after obtaining written informed consent. T2S (3 mm slice thickness) was acquired first in three orthogonal planes followed by thin-slice T2DLR (2 mm slice thickness) in axial plane. Acquisition time of axial conventional T2S was 4:12 min compared to 4:37 min for T2DLR. Imaging datasets were evaluated by two radiologists using a Likert-scale ranging from 1-4, with 4 being the best regarding the following parameters: sharpness, lesion detectability, artifacts, overall image quality, and diagnostic confidence. Furthermore, preference of T2S versus T2DLR was evaluated. RESULTS: The mean patient age was 68 ± 8 years. Sharpness of images and lesion detectability were rated better in T2DLR with a median of 4 versus a median of 3 in T2S (p < 0.001 for both readers). Image noise was evaluated to be significantly worse in T2DLR as compared to T2S (p < 0.001 and p = 0.021, respectively). Overall image quality was also evaluated to be superior in T2DLR versus T2S with a median of 4 versus 3 (p < 0.001 for both readers). Both readers chose T2DLR in 29 cases as their preference. CONCLUSIONS: Thin-slice T2DLR of the prostate provides a significant improvement of image quality without significant prolongation of acquisition time. | F49: Cancers | G49: Journal Article | H49: YES | I49: UNCERTAIN | K49: DL reconstruction prostate MRI, prospective; lesion detectability rated - check downstream task | L49: 46313 | M49: =IF(OR(I49="INCLUDE",I49="UNCERTAIN"),"RETRIEVE",IF(I49="EXCLUDE","EXCLUDE",""))
A50: 47 | B50: LIB-05128 | C50: 2023 | D50: DEEP LEARNING AUGMENTED DETECTION OF FLAT LESIONSON WHITE LIGHT CYSTOSCOPY | E50: INTRODUCTION AND OBJECTIVE: While-light cystoscopy (WLC) has inadequate performance for detection of flat lesions such as carcinoma in situ. Blue-light cystoscopy (BLC) has improved flat-lesion detection, however adoption is modest due to equipment cost, drug instillation, and user experience. Here we develop a non-invasive, deep learning-based algorithm to augment WLC flat lesion detection by using blue-light informed transfer learning. METHODS: CystoFlatNet was developed based on CystoNet, a deep learning platform for WLC bladder cancer detection. CystoNet was enhanced to augment flat lesion detection in two stages. First, a WLC image was input into a BLC domain using domain adaption of Cycle- GAN. Second, a region of interest (ROI) detector was used to segment the regions within the transferred images occupied by a flat lesion. Transfer learning was applied to embed features learned from both WLC and BLC into the model weights. Algorithm outputs included an outline deployed in WLC and a “mock” BLC output. For algorithm development, images of WLC and BLC matches from 50 subjects with flat lesions were selected and annotated. A training set consisting of 40 subjects and a test set of 10 subjects were used. Training was performed on WLC and BLC images. WLC was the only input used for validation. Per-lesion sensitivity was determined and performance compared to CystoNet. RESULTS: CystoFlatNet detected flat lesions on WLC with a 90% per-lesion sensitivity (9/10). In comparison, the previously trained CystoNet had a 30% per-lesion sensitivity (3/10). Large accuracy gains were obtained in ROI overlap and visual guidance in the blue-light domain (Figure 1). CONCLUSIONS: We have developed a deep-learning algorithm that shows promise in WLC flat lesion detection. CystoFlatNet may aid in diagnostic decision-making and could serve as a non-invasive, accessible alternative to available adjunct technologies. Validation in a large prospective cohort is needed to further evaluate CystoFlatNet performance. (Figure Presented). | F50: J. Urol. | G50: JOUR; Conference Abstract | H50: YES | I50: EXCLUDE | J50: Ineligible publication type | K50: CONFERENCE_ABSTRACT | L50: 46313 | M50: =IF(OR(I50="INCLUDE",I50="UNCERTAIN"),"RETRIEVE",IF(I50="EXCLUDE","EXCLUDE",""))
A51: 48 | B51: LIB-04332 | C51: 2016 | D51: Clinical and genomic characterization of metastatic small cell/neuroendocrine prostate cancer (SCNC) and intermediate atypical prostate cancer (IAC): Results from the SU2C/PCF/AACRWest Coast Prostate Cancer Dream Team (WCDT) | E51: Background: SCNC and a novel pathologic subtype, IAC, comprise a growing proportion of mCRPC patients resistant to androgen signaling inhibitors such as Abiraterone (Abi) or Enzalutamide (Enz). We sought to characterize these nonadenocarcinoma (adeno) subtypes in a prospective biopsy study. Methods: Eligible mCRPC pts underwent a metastasis biopsy (bx), and were followed for clinical outcomes. Tissue was both frozen and formalin fixed/paraffin embedded (FFPE). Independent review of FFPE specimens was undertaken by 3 pathologists. Frozen specimens underwent laser capture microdissection prior to RNA sequencing (seq). Machine learning was used to derive histologyspecific expression signatures. Signature accuracy was evaluated with leavepairout crossvalidation and application to an independent data set. Results: 226 of 300 planned mCRPC pts (74% resistant to Abi and/or Enz) have undergone bx (including 123 bone, 61 node, and 23 liver bx) with a 78% evaluable biopsy rate. Adeno was identified in 39%, nonadeno in 41% (SCNC in 12%, IAC in 29%), with other mixtures in the remaining 20%. Median overall survival (OS) from time of biopsy for pts with nonadeno histologies was 12.8 months (mos) [ IAC OS = 19.1 mos; SCNC OS = 12.8 mos] versus 25.8 mos in adeno pts (p=0.023). RNAseq data are available from 94 bx. Transcriptional signatures were developed which accurately distinguish adeno, SCNC and IAC. IAC appears to have a signature intermediate between adeno and SCNC. When applied to an independent data set (Beltran et al, Ca Disc 2011), these transcriptional signatures identified SCNC with 100% accuracy, and predict for IAC differentiation in a subset of nonSCNC tumors. Conclusions: A majority of CRPC metastases exhibit nonadenocarcinoma features, which are associated with a shortened survival. IAC and SCNC are genomically distinct, and newly derived transcriptional signatures based on these bx can be used to identify SCNC in an independent data set. Integration of whole exome with RNAseq data are ongoing to identify pathways upregulated in IAC and SCNC. | F51: J. Clin. Oncol. | G51: JOUR; Conference Abstract | H51: YES | I51: EXCLUDE | J51: Ineligible publication type | K51: CONFERENCE_ABSTRACT | L51: 46313 | M51: =IF(OR(I51="INCLUDE",I51="UNCERTAIN"),"RETRIEVE",IF(I51="EXCLUDE","EXCLUDE",""))
A52: 49 | B52: LIB-00529 | C52: 2019 | D52: 2019 Research Workshop: Treatment of Oligometastatic Disease - Closer to the Cure | E52: The proceedings contains 18 papers. The topics discussed include: Plasma Circulating Tumor HPV DNA for Early Detection of Cancer Recurrence in HPV-associated Oropharyngeal Cancer;A Validated Radiomics T Cell Score Predicts Response to Multi-site SBRT Combined with Pembrolizumab;Dosimetric Comparison of Biologically-Guided Radiotherapy and X-ray-Guided Stereotactic Ablative Radiotherapy for Oligometastatic Prostate Cancer;Multi-Site SBRT and Sequential Pembrolizumab: Treated Metastasis Control and Immune-Related Expression Predict Outcomes;Phase 1b study of stereotactic body radiation therapy in combination with systemic therapy in patients with extracranial oligometastatic renal cell carcinoma;Management of Oligometastatic Squamous Cell Carcinoma of the Head and Neck;Number of Metastatic Organ Sites and Survival by Molecular Profile in Lung Adenocarcinoma;Stereotactic Ablative Radiation Therapy for Oligometastatic Non-Small Cell Lung Cancer, Subset Analysis of a Prospective Phase II Clinical Trial;Increased Biologically Effective Dose (BED) To The Primary Tumor Improves Survival in Patients with Oligometastatic NSCLC: A Retrospective Dose Response Analysis;Radium 223 Dichloride in Combination with Androgen Deprivation Therapy and Stereotactic Body Radiation Therapy for Patients with Stage IV Oligometastatic Castration Sensitive Prostate Cancer: Clinical Trial in Progress;Platform Phase I Study Investigating the Safety of Multisite Stereotactic Body Radiotherapy with Immuno-Oncology Agents for the Treatment of Metastatic Advanced Solid Tumors;Radiotherapy In The Definitive Management Of Oligometastatic Prostate Cancer;Predictive factors and survival outcomes with stereotactic body radiation therapy in treatment of oligometastases in colorectal cancer;Long-term Disease Control and Survival Observed after Stereotactic Body Radiotherapy for Oligometastatic Breast Cancer;Molecular Profiling of Oligometastases and Artificial Intelligence-based Model for Predicting Treatment Outcome in Advance Prostate Cancer;Advance SBRT approaches for patients with oligometastases;Neoadjuvant Stereotactic Ablative and Hypofractionated Radiotherapy for Oligometastatic NSCLC | F52: Int. J. Radiat. Oncol. Biol. Phys. | G52: JOUR; Conference Review | H52: YES | I52: EXCLUDE | J52: Ineligible publication type | K52: CONFERENCE_ABSTRACT | L52: 46313 | M52: =IF(OR(I52="INCLUDE",I52="UNCERTAIN"),"RETRIEVE",IF(I52="EXCLUDE","EXCLUDE",""))
A53: 50 | B53: LIB-04530 | C53: 2018 | D53: Entering an era of radiogenomics in prostate cancer risk stratification. | E53: Radiogenomics is a field that amalgamates data from genomics and imaging techniques in order to derive clinically meaningful trends. In this article, we discuss the importance of prostate cancer risk classification and how data derived from genomic testing and multi-parametric magnetic resonance imaging (mpMRI) can be integrated into clinical decision-making processes with a focus on active surveillance (AS). Finally, we describe an ongoing prospective trial (Miami MAST trial) which incorporates imaging (mpMRI) and radiomics data in patients who are on AS for prostate cancer. | F53: Translational andrology and urology | G53: Journal Article; Review | H53: YES | I53: EXCLUDE | J53: Ineligible publication type | K53: NON_PRIMARY_PUBLICATION | L53: 46313 | M53: =IF(OR(I53="INCLUDE",I53="UNCERTAIN"),"RETRIEVE",IF(I53="EXCLUDE","EXCLUDE",""))
A54: 51 | B54: LIB-03540 | C54: 2026 | D54: Development and validation of a risk prediction model for chemical cystitis in patients with non-muscle-invasive bladder cancer undergoing intravesical instillation | E54: Objective: To develop and validate a risk prediction model for Chemical cystitis in patients with non-muscle-invasive bladder cancer (NMIBC) undergoing intravesical instillation. Methods: This study retrospectively enrolled 225 patients with NMIBC who received intravesical instillation between January 2024 and January 2026. Predictive variables, including demographic characteristics, oncological features, medical history, treatment-related factors, and procedural anatomy, were collected. Feature selection was performed using the Least Absolute Shrinkage and Selection Operator (LASSO) regression from 18 candidate variables. A multivariable logistic regression model was constructed based on the selected variables and visualized as a risk prediction nomogram. The model’s performance was evaluated and validated using the Area Under the Curve (AUC), calibration curves, and Decision Curve Analysis (DCA) to assess discrimination, calibration, and clinical utility. Results: Five independent predictors were identified from the candidate variables through LASSO and multivariable logistic regression analysis: type of instillation agent, tumor multifocality, retention time of the agent, bladder capacity, and tumor grade. The predictive model demonstrated robust discriminative ability in both the training and validation cohorts, with AUC values of 0.840 and 0.868, respectively. Calibration curves showed high consistency between the predicted and observed risks, and DCA further confirmed the model’s positive net benefit in clinical decision-making. Conclusion: We successfully developed and validated a practical nomogram for the individualized prediction of Chemical cystitis risk in patients with NMIBC. This tool can assist clinicians in identifying high-risk patients prior to treatment, thereby enabling more targeted monitoring and preventive strategies. This study is limited by its single-center retrospective design, and external prospective validation is warranted. | F54: Oncol. Rev. | G54: JOUR; Article | H54: YES | I54: EXCLUDE | J54: Retrospective-only/ineligible design | K54: RETROSPECTIVE_ONLY | L54: 46313 | M54: =IF(OR(I54="INCLUDE",I54="UNCERTAIN"),"RETRIEVE",IF(I54="EXCLUDE","EXCLUDE",""))
A55: 52 | B55: LIB-00451 | C55: 2026 | D55: Prostate MRI Analysis by Radiologists and Artificial Intelligence - Disease Identification and Guided Management | E55: Aim: To assess whether artificial intelligence is non‐inferior to radiologists in thediagnosis of clinically significant prostate cancer on MRI.ObjectivesPrimary1. To compare the proportion of men who have clinically significant prostate cancerdetected on MRI using AI ± targeted biopsy with radiologists ± targeted biopsy.Secondary 1. To compare the proportion of men who have clinically insignificant prostate cancerdetected on MRI using AI ± targeted biopsy with radiologists ± targeted biopsy. 2. To compare the proportion of men with non‐suspicious MRIs for AI vs radiologists. 3. To compare the proportion of men with indeterminately scored MRI as reported by AIvs radiologists. 4. To compare the diagnostic test performance of AI vs radiologist. 5. To compare the additive value of AI when used together with a radiologistinterpretation (summative of all identified lesions) compared to a radiologistalone. 6. To compare the additive value of AI when used together with a radiologistinterpretation (where the radiologist can interact with the AI system by acceptingor rejecting AI‐identified lesions) compared to a radiologist alone. 7. To determine the frequency of AI failures. 8. To compare treatment eligibility decisions between AI and Radiologist. 9. To compare the cost‐effectiveness of unblinded AI interpreted by the radiologistcompared to radiologist alone for prostate cancer detection, and AI alone vs.radiologist alone, and a 3‐arm analysis considering all three.Design:Prospective, international, within‐patient, multi‐centre, level‐1 evidence trial inparticipants referred to hospital with a clinical suspicion of prostate cancer. | F55: https://clinicaltrials.gov/study/NCT07647445 | G55: JOUR; Trial registry record | H55: YES | I55: EXCLUDE | J55: Protocol/no results | K55: PROTOCOL_NO_RESULTS | L55: 46313 | M55: =IF(OR(I55="INCLUDE",I55="UNCERTAIN"),"RETRIEVE",IF(I55="EXCLUDE","EXCLUDE",""))
A56: 53 | B56: LIB-03338 | C56: 2026 | D56: Immune checkpoint inhibitors in urothelial carcinoma: a practical framework for patient selection, toxicity management, response assessment, and treatment sequencing. | E56: INTRODUCTION: Managing urothelial carcinoma with immune checkpoint inhibitors requires addressing issues beyond clinical outcomes. Implementation difficulties affect most patients, predictive biomarkers show limited utility, and treatment discontinuation from toxicity remains problematic. AREAS COVERED: This article integrates clinical trials, systematic reviews, health-system evaluations, and guidelines from 2016 to 2025. We detail limitations of programmed death-ligand 1 (PD-L1) expression, panel-based tumor mutational burden (TMB), clinic-ready toxicity pathways, immune-appropriate response criteria (iRECIST), pseudoprogression, hyperprogression, post-ICI sequencing (FGFR3 alterations, enfortumab vedotin-based therapy, chemotherapy, trials), and delivery models (navigation, electronic patient-reported outcomes, telemedicine, payment structures). EXPERT OPINION: Optimizing systemic frameworks for immunotherapy care requires careful evaluation of functional status, protocols for immune-related adverse events management, standardization for assessments of clinical responses, and ensuring equitable access to care. ctDNA and AI-assisted radiomics are promising adjuncts to clinical care, but still require multi-center prospective validation before adoption into routine practice. | F56: Expert review of anticancer therapy | G56: Journal Article; Review | H56: YES | I56: EXCLUDE | J56: Ineligible publication type | K56: NON_PRIMARY_PUBLICATION | L56: 46313 | M56: =IF(OR(I56="INCLUDE",I56="UNCERTAIN"),"RETRIEVE",IF(I56="EXCLUDE","EXCLUDE",""))
A57: 54 | B57: LIB-08550 | C57: 2026 | D57: Differentiating Prostate Cancer from Normal Tissue Using Radiomics from Ga-68 PSMA PET/CT: A Comparative Study of Twelve Machine Learning Classifiers | E57: Objective To evaluate the feasibility and robustness of radiomics-based machine learning on gallium-68 prostate-specific membrane antigen positron emission tomography/computed tomography for differentiating histopathologically confirmed prostate cancer from normal prostatic tissue, with emphasis on control-group composition and class balancing. Materials and Methods This retrospective study included 73 subjects (38 prostate cancer, 35 controls). Manual prostate segmentation yielded 186 radiomics features, of which 127 remained after removal of invalid and zero-variance features. Four analyses were performed: 38 cancer/14 normal with synthetic minority oversampling technique (SMOTE), 38/24 with SMOTE, 38/35 with SMOTE, and 38/35 without SMOTE. Twelve classifiers were evaluated using 10,000 repeated random 80/20 train-test partitions. Balanced accuracy was the primary metric. Classifier differences were assessed using paired bootstrap confidence intervals (CIs) and sign-flipping permutation tests with Benjamini-Hochberg correction. Results Performance varied with control-group composition. CoarseKNN achieved the highest balanced accuracy in the 38/14 analysis (0.880 +/- 0.111) and both 38/35 analyses (0.817 +/- 0.097 with SMOTE; 0.812 +/- 0.097 without SMOTE). In the 38/24 analysis, MediumKNN performed best (0.810 +/- 0.113), followed by CosineKNN (0.807 +/- 0.113) and CoarseKNN (0.798 +/- 0.115). MediumKNN significantly outperformed CoarseKNN (mean paired difference, 0.0126; 95% CI, 0.0108-0.0144; false discovery rate-adjusted p < 0.001). Conclusion K-nearest neighbors (KNN) classifiers showed the most consistent performance, although the best classifier varied with cohort composition. The biopsy-negative analysis provided a clinically relevant control comparison. However, the small sample size, heterogeneous nonbiopsy controls, and absence of external validation limit generalizability. Larger prospective multicenter studies with direct benchmarking against PROMISE and PRIMARY score are required before clinical translation. | F57: WORLD JOURNAL OF NUCLEAR MEDICINE | G57: JOUR | H57: YES | I57: EXCLUDE | J57: Retrospective-only/ineligible design | K57: RETROSPECTIVE_ONLY | L57: 46313 | M57: =IF(OR(I57="INCLUDE",I57="UNCERTAIN"),"RETRIEVE",IF(I57="EXCLUDE","EXCLUDE",""))
A58: 55 | B58: LIB-01809 | C58: 2023 | D58: ARCHERY: a prospective observational study of artificial intelligence-based radiotherapy treatment planning for cervical, head and neck and prostate cancer - study protocol. | E58: INTRODUCTION: Fifty per cent of patients with cancer require radiotherapy during their disease course, however, only 10%-40% of patients in low-income and middle-income countries (LMICs) have access to it. A shortfall in specialised workforce has been identified as the most significant barrier to expanding radiotherapy capacity. Artificial intelligence (AI)-based software has been developed to automate both the delineation of anatomical target structures and the definition of the position, size and shape of the radiation beams. Proposed advantages include improved treatment accuracy, as well as a reduction in the time (from weeks to minutes) and human resources needed to deliver radiotherapy. METHODS: ARCHERY is a non-randomised prospective study to evaluate the quality and economic impact of AI-based automated radiotherapy treatment planning for cervical, head and neck, and prostate cancers, which are endemic in LMICs, and for which radiotherapy is the primary curative treatment modality. The sample size of 990 patients (330 for each cancer type) has been calculated based on an estimated 95% treatment plan acceptability rate. Time and cost savings will be analysed as secondary outcome measures using the time-driven activity-based costing model. The 48-month study will take place in six public sector cancer hospitals in India (n=2), Jordan (n=1), Malaysia (n=1) and South Africa (n=2) to support implementation of the software in LMICs. ETHICS AND DISSEMINATION: The study has received ethical approval from University College London (UCL) and each of the six study sites. If the study objectives are met, the AI-based software will be offered as a not-for-profit web service to public sector state hospitals in LMICs to support expansion of high quality radiotherapy capacity, improving access to and affordability of this key modality of cancer cure and control. Public and policy engagement plans will involve patients as key partners. | F58: BMJ open | G58: Journal Article; Research Support, N.I.H., Extramural; Research Support, Non-U.S. Gov't; Clinical Trial Protocol | H58: YES | I58: EXCLUDE | J58: Wrong population | K58: WRONG_POPULATION | L58: 46313 | M58: =IF(OR(I58="INCLUDE",I58="UNCERTAIN"),"RETRIEVE",IF(I58="EXCLUDE","EXCLUDE",""))
A59: 56 | B59: LIB-05746 | C59: 2026 | D59: Machine learning in bleeding risk assessment for low-molecular-weight heparin or fondaparinux: a predictive model study. | E59: BACKGROUD: No universally accepted model exists for predicting bleeding risk in patients receiving low-molecular-weight heparin or fondaparinux. OBJECTIVE: This study leveraged seven machine learning algorithms to build a short-term bleeding risk prediction platform for this population. METHODS: This retrospective real-world observational study included hospitalized patients who received low-molecular-weight heparin or fondaparinux between January 2022 and December 2023. After applying predefined criteria, the cohort were randomly split into training (70%) and validation (30%) sets. Predictors were identified using LASSO regression. Seven machine learning models, including Logistic Regression (LR), Support Vector Machine (SVM), Gradient Boosting Machine (GBM), Neural Network (NN), extreme gradient boosting (XGBoost), adaptive boosting (AdaBoost), and CatBoost, were developed and evaluated. The best-performing model was implemented as an internal web-based bleeding risk prediction tool. RESULTS: Among 1,691 hospitalized patients receiving low-molecular-weight heparin or fondaparinux, 126 (7.5%) experienced bleeding events. The cohort was randomly split into training (n = 1,184) and validation (n = 507) sets. LASSO regression identified 12 predictors, including surgical site, pre-medication INR, hemoglobin, platelet count, renal function, body mass index (BMI), indication, and comorbidities. Seven machine learning models were developed and evaluated. In the validation cohort, CatBoost achieved the best discrimination (AUC = 0.659), followed by XGBoost (AUC = 0.651) and LR (AUC = 0.622). CatBoost also demonstrated the highest accuracy (86.0%) and F1 score (0.297), with strong specificity (89.2%) but limited sensitivity (42.9%). Although all models showed robust negative predictive performance (PR-AUC > 0.93), positive predictive capacity was modest (PR-AUC < 0.20) in validation. Based on its overall performance, CatBoost was deployed as an internal web-based bleeding risk calculator. CONCLUSIONS: CatBoost emerged as the optimal model among those tested for predicting bleeding risk in patients receiving low-molecular-weight heparin or fondaparinux, demonstrating modest but superior discrimination, acceptable calibration, and favorable clinical utility. However, the model had limited ability to correctly identify patients who experienced bleeding, as indicated by low positive predictive performance. Given its high negative predictive value, it was better suited for ruling out rather than confirming bleeding risk. A web-based risk calculator based on CatBoost has been developed for internal use. Nevertheless, prospective multicenter validation is required before clinical implementation. | F59: Scientific reports | G59: Journal Article; Observational Study | H59: YES | I59: EXCLUDE | J59: Wrong population | K59: WRONG_POPULATION | L59: 46313 | M59: =IF(OR(I59="INCLUDE",I59="UNCERTAIN"),"RETRIEVE",IF(I59="EXCLUDE","EXCLUDE",""))
A60: 57 | B60: LIB-02525 | C60: 2025 | D60: Applications and Performance of Artificial Intelligence in Spinal Metastasis Imaging: A Systematic Review. | E60: Background: Spinal metastasis is the third most common site for metastatic localization, following the lung and liver. Manual detection through imaging modalities such as CT, MRI, PET, and bone scintigraphy can be costly and inefficient. Preliminary artificial intelligence (AI) techniques and computer-aided detection (CAD) systems have attempted to improve lesion detection, segmentation, and treatment response in oncological imaging. The objective of this review is to evaluate the current applications of AI across multimodal imaging techniques in the diagnosis of spinal metastasis. Methods: Databases like PubMed, Scopus, Web of Science Advance, Cochrane, and Embase (Ovid) were searched using specific keywords like 'spine metastases', 'artificial intelligence', 'machine learning', 'deep learning', and 'diagnosis'. The screening of studies adhered to the PRISMA guidelines. Relevant variables were extracted from each of the included articles such as the primary tumor type, cohort size, and prediction model performance metrics: area under the receiver operating curve (AUC), accuracy, sensitivity, specificity, internal validation and external validation. A random-effects meta-analysis model was used to account for variability between the studies. Quality assessment was performed using the PROBAST tool. Results: This review included 39 studies published between 2007 and 2024, encompassing a total of 6267 patients. The three most common primary tumors were lung cancer (56.4%), breast cancer (51.3%), and prostate cancer (41.0%). Four studies reported AUC values for model training, 16 for internal validation, and five for external validation. The weighted average AUCs were 0.971 (training), 0.947 (internal validation), and 0.819 (external validation). The risk of bias was the highest in the analysis domain, with 22 studies (56%) rated high risk, primarily due to inadequate external validation and overfitting. Conclusions: AI-based approaches show promise for enhancing the detection, segmentation, and characterization of spinal metastatic lesions across multiple imaging modalities. Future research should focus on developing more generalizable models through larger and more diverse training datasets, integrating clinical and imaging data, and conducting prospective validation studies to demonstrate meaningful clinical impact. | F60: Journal of clinical medicine | G60: Journal Article; Review | H60: YES | I60: EXCLUDE | J60: Ineligible publication type | K60: NON_PRIMARY_PUBLICATION | L60: 46313 | M60: =IF(OR(I60="INCLUDE",I60="UNCERTAIN"),"RETRIEVE",IF(I60="EXCLUDE","EXCLUDE",""))
A61: 58 | B61: LIB-02077 | C61: 2024 | D61: Predicting Biochemical Recurrence of Prostate Cancer Post-Prostatectomy Using Artificial Intelligence: A Systematic Review. | E61: Background/Objectives: Biochemical recurrence (BCR) after radical prostatectomy (RP) is a significant predictor of distal metastases and mortality in prostate cancer (PCa) patients. This systematic review aims to evaluate the accuracy of artificial intelligence (AI) in predicting BCR post-RP. Methods: Adhering to PRISMA guidelines, a comprehensive literature search was conducted across Medline, Embase, Web of Science, and IEEE Xplore. Studies were included if they utilised AI to predict BCR in patients post-RP. Studies involving patients who underwent radiotherapy or salvage RP were excluded. This systematic review was registered on PROSPERO (International prospective register of systematic reviews) under the ID CRD42023482392. Results: After screening 9764 articles, 24 met the inclusion criteria. The included studies involved 27,216 patients, of whom 7267 developed BCR. AI algorithms developed using radiological parameters demonstrated higher predictive accuracy (median AUROC of 0.90) compared to algorithms based solely on pathological variables (median AUROC of 0.74) or clinicopathological variables (median AUROC of 0.81). According to the Prediction Model Risk of Bias Assessment Tool (PROBAST), the overall risk of bias was unclear in three studies due to ambiguous inclusion criteria and the exclusion of many patients because of missing follow-up data. In seven studies, the developed AI outperformed or was at least equivocal to traditional methods of BCR prediction. Conclusions: AI shows promise in predicting BCR post-RP, particularly when radiological data were used in its development. However, the significant variability in AI performance and study methodologies highlights the need for larger, standardised prospective studies with external validation prior to clinical application. | F61: Cancers | G61: Journal Article; Review | H61: YES | I61: EXCLUDE | J61: Ineligible publication type | K61: NON_PRIMARY_PUBLICATION | L61: 46313 | M61: =IF(OR(I61="INCLUDE",I61="UNCERTAIN"),"RETRIEVE",IF(I61="EXCLUDE","EXCLUDE",""))
... A69: 66 | B69: LIB-00202 | C69: 2022 | D69: Image-guided focal dose escalation in patients with primary prostate cancer treated with primary external beam hypofractionated radiation therapy (HypoFocal) – a prospective, multicenter, randomized phase III study | E69: INTERVENTION: Group 1: RT prostate: 35 Gy in 7 Gy per fraction RT seminal vesicles: 30 Gy in 6 Gy per fraction RT on the intraprostatic tumour mass (ITM): 40 – 42 Gy in 8 ‐ 8.4 Gy per fraction. If the boost volume is =10 ml and/ or = 1/3 of the prostate, the dose on the ITM has to be restrained to 40 Gy in 8 Gy per fraction. The dose escalation has to be performed by keeping the strict dose constraints for the organs at risk. Technique: IMRT/IGRT/SBRT/SIB Duration: 5 fractions, 3 week Group 2: RT prostate: 60‐62 Gy in 3‐3.1 Gy per fraction RT seminal vesicles: 46.4 Gy in 2.32 Gy per fraction in 5 fractions per week Technique: IMRT/IGRT/SIB Duration: 20 fractions, 4 weeks. CONDITION: Prostate Cancer PRIMARY OUTCOME: Primary endpoint is relapse free survival (RFS), defined as time from randomization to relapse or death. Relapse free survival times will be censored at the time seen last alive without relapse. For the definition of relapse see 2.3.1. SECONDARY OUTCOME: ‐ Time to local failure; after randomization. Local recurrences have to be confirmed by biopsy. ; ‐ Metastatic free survival after randomization, (all metastases have to be confirmed by imaging, preferably by PSMA‐PET/CT or mpMR imaging) ; ‐ Overall (OS) and prostate cancer specific (PCSS) survival after randomization ; ‐ Time to biochemical failure after randomization (phoeni Xdefinition) ; ‐ Patient reported acute quality of life after treatment, at month 3 and month 6 after randomization (QOL: EPIC‐26 and IPSS) ; ‐ Patient reported late quality of life at months 9,12,15,18 21, 24, 30, 36, 42, 48 and months 54, 60, 66, 72, 78, 84 up to 90 after randomization (QOL: EPIC‐26 and IPSS) ; ‐ Cumulative acute genitourinary (GU) and gastrointestinal (GI) toxicities during and up to 3 months after RT using the CTCAEv5.0 criteria ; ‐ Cumulative chronic GU and GI toxicities after RT using the CTCAEv5.0 criteria ; ‐ Feasibility and adherence to dose constraints by measuring the ratio between: patients with fulfilled dose constraints and prescription doses / recruited patients ; ‐ Characterization of safety: adverse events ; ‐ Translational side projects include: assessment of immune response, multidimensional biomarkers for risk prediction, comparison and evaluation of PSMA‐PET and mpMRI in treatment planning for PCa patients including artificial intelligence tools for automated image interpretation, strategies for patients’ empowerment and involvement (all side projects are defined in separate protocols of the clinical part of the HypoFocal‐SBRT study) INCLUSION CRITERIA: 1. Histologically confirmed adenocarcinoma of the prostate (histological confirmation can be based on tissue taken at any time, but a re‐biopsy should be considered if the biopsy is more than 12 months old) 2. Primary localized PCa (cN0 and cM0 in mpMRI and PSMA‐PET): ‐ high‐ or very high‐risk according to NCCN v2.2021 (see 20.3) OR ‐ unfavorable intermediate‐risk disease according to NCCN v2.2021 (see 20.3) 3. Signed written informed consent for this study 4. Age >18 years 5. Previously conducted PSMA‐PET/CT and mpMRI scans or PSMA‐PET/MR, fulfilling standard requirements for PCa (see also 6.5) 6. ECOG Performance score 0 or 1 7. IPSS Score =15 8. Prostate volume = 75 ml at RT planning | F69: https://trialsearch.who.int/Trial2.aspx?TrialID=DRKS00022915 | G69: JOUR; Trial registry record | H69: YES | I69: EXCLUDE | J69: Protocol/no results | K69: PROTOCOL_NO_RESULTS | L69: 46313 | M69: =IF(OR(I69="INCLUDE",I69="UNCERTAIN"),"RETRIEVE",IF(I69="EXCLUDE","EXCLUDE",""))
A70: 67 | B70: LIB-06060 | C70: 2026 | D70: Artificial Intelligence Remote Patient Monitoring for Predicting Overall Survival for Patients Undergoing Radical Cystectomy for Bladder Cancer: Exploratory Analysis of the Prospective Trial. | E70: BACKGROUND: Previous studies have highlighted the benefits of using artificial intelligence-powered remote patient monitoring (AI RPM) in detecting health changes across various disease cohorts. However, the use of AI RPM for identifying health deteriorations in patients following major surgical procedures remains underexplored. OBJECTIVE: This exploratory analysis of a prospective trial aims to assess how AI RPM can enhance the predictive performance of 35-month post-radical cystectomy (RC) mortality risk. Our approach highlights the importance of RPM features in improving prediction accuracy and provides interpretable model outputs to enhance clinical understanding and transparency. METHODS: We used patient data from a multicenter RC trial conducted in the United Kingdom for model training and validation. Two gradient-boosted machine learning models were developed: one using only clinical-pathological (CP) features and another incorporating both CP and remote patient monitoring (RPM) features (CP+RPM). RPM features are measured by wrist-worn pedometers and surveys. The predictive accuracy of the CP+RPM model was compared with both the CP model and a clinically used nomogram, both of which relied solely on traditional clinical features. We used 200 bootstrap iterations, with 70% of the data used for training and 30% for testing. Shapley Additive Explanations were applied to interpret model results and provide insights into the relative importance of features, improving transparency and understanding of the predictions. RESULTS: A total of 252 patients (33 deaths) from 9 UK centers were included in the analysis. We examined 108 RPM features and 24 CP features for model training. In correlation analysis, only 9 CP features showed coefficients larger than 0.1, compared with 36 RPM features with stronger correlations. The CP+RPM model achieved an area under the receiver operating characteristic curve of 0.77, reflecting a 9% and 10% absolute (13% and 15% relative) improvement over the CP and nomogram models, respectively. Similarly, it outperformed in terms of the area under the precision-recall curve, with a score of 0.44, marking a 6% and 17% absolute (16% and 63% relative) increase compared with the CP and nomogram model. Shapley Additive Explanations analysis revealed that the most significant contributors to mortality prediction were mobility-related RPM features, such as the 30-second chair-to-stand test results and daily step count variance, which reflected the general activity levels of individuals. CONCLUSIONS: Our study demonstrates that RPM features significantly enhance long-term survival prediction for post-RC patients, offering a valuable addition to traditional clinical data. The integration of AI with RPM enables more individualized and dynamic tracking of recovery, improving prediction accuracy and fostering a patient-centered care model that has the potential to be applied across a broader range of surgeries and conditions. | F70: JMIR AI | G70: Journal Article | H70: YES | I70: UNCERTAIN | L70: 46313 | M70: =IF(OR(I70="INCLUDE",I70="UNCERTAIN"),"RETRIEVE",IF(I70="EXCLUDE","EXCLUDE",""))
A71: 68 | B71: LIB-01377 | C71: 2022 | D71: Higher TYROBP and lower SOX6 as predictive biomarkers for poor prognosis of clear cell renal cell carcinoma: A pilot study. | E71: BACKGROUND: Clear cell renal carcinoma (ccRCC) is the most common subtype of renal cancer, accounting for approximately 75% of all histological types of renal cancer, and is the leading cause of death from renal cancer. However, the molecular mechanism of tyrosine kinase binding protein (TYROBP) and sex-determining region Y Box-6 (SOX6) in the ccRCC was not precise. METHODS: Bioinformatics analysis was performed to explore the hub role of TYROBP and SOX6 on the ccRCC. A total of 6 patients with clear cell renal cell carcinoma (ccRCC) were recruited. HE staining was performed to observe the pathology result of ccRCC. Immunohistochemistry and Immunofluorescence assay was made to detect the protein expression of TYROBP. Total RNA was extracted using TRIzol to examine the mRNA expression of TYROBP via the Real time quantitative polymerase chain reaction. The strong correlation between the expression of TYROBP and the survival time of ccRCC patients was performed by the BP neural network and support vector machine. RESULTS: Compared with the control group, the expression of SOX6 was downregulated in the samples with ccRCC. However, the expression of TYROBP was higher in the samples with ccRCC than in the control group. Compared with the patients with high SOX6 expression, the patients with low SOX6 expression have a poor survival prognosis (HR=0.39, P < .05). However, the patients with high TYROBP expression have a shorter survival time than the patients with low TYROBP expression (HR=1.66, P < .05). The genes related with TYROBP and SOX6 are mainly enriched in the regulation of cell activation, leukocyte activation, negative regulation of cell activation, myeloid leukocyte activation, positive regulation of response to external stimulus, immune response-regulating signaling pathway. The interaction between TYROBP, SOX6, and kidney neoplasms was drawn, and the inference score of TYROBP and SOX6 on the kidney neoplasms was high. CONCLUSION: In conclusion, TYROBP is highly expressed in renal clear cell carcinoma, and when this molecule is highly expressed, the survival prognosis of renal carcinoma is poor. TYROBP and SOX6 may be potential targets for diagnosing and treating renal clear cell carcinoma. | F71: Medicine | G71: Journal Article | H71: YES | I71: EXCLUDE | J71: No eligible AI/ML system | K71: NO_RELEVANT_AI | L71: 46313 | M71: =IF(OR(I71="INCLUDE",I71="UNCERTAIN"),"RETRIEVE",IF(I71="EXCLUDE","EXCLUDE",""))
A72: 69 | B72: LIB-01449 | C72: 2023 | D72: Stimulated Raman histology, a novel method to allow for rapid pathologic examination of unprocessed, fresh prostate biopsies. | E72: INTRODUCTION: Delay between targeted prostate biopsy (PB) and pathologic diagnosis can lead to a concern of inadequate sampling and repeated biopsy. Stimulated Raman histology (SRH) is a novel microscopic technique allowing real-time, label-free, high-resolution microscopic images of unprocessed, unsectioned tissue. This technology holds potential to decrease the time for PB diagnosis from days to minutes. We evaluated the concordance of pathologist interpretation of PB SRH as compared with traditional hematoxylin and eosin (H&E) stained slides. METHODS: Men undergoing prostatectomy were included in an IRB-approved prospective study. Ex vivo 18-gauge PB cores, taken from prostatectomy specimen, were scanned in an SRH microscope (NIO; Invenio Imaging) at 20 microns depth using two Raman shifts: 2845 and 2930 cm-1 , to create SRH images. The cores were then processed as per normal pathologic protocols. Sixteen PB containing a mix of benign and malignant histology were used as an SRH training cohort for four genitourinary pathologists, who were then tested on a set of 32 PBs imaged by SRH and processed by traditional H&E. Sensitivity, specificity, accuracy, and concordance for prostate cancer (PCa) detection on SRH relative to H&E were assessed. RESULTS: The mean pathologist accuracy for the identification of any PCa on PB SRH was 95.7%. In identifying any PCa or ISUP grade group 2-5 PCa, a pathologist was independently able to achieve good and very good concordance (κ: 0.769 and 0.845, respectively; p < 0.001). After individual assessment was completed a pathology consensus conference was held for the interpretation of the PB SRH; after the consensus conference the pathologists' concordance in identifying any PCa was also very good (κ: 0.925, p < 0.001; sensitivity 95.6%; specificity 100%). CONCLUSION: SRH produces high-quality microscopic images that allow for accurate identification of PCa in real-time without need for sectioning or tissue processing. The pathologist performance improved through progressive training, showing that ultimately high accuracy can be obtained. Ongoing SRH evaluation in the diagnostic and treatment setting hold promise to reduce time to tissue diagnosis, while interpretation by convolutional neural network may further improve diagnostic characteristics and broaden use. | F72: The Prostate | G72: Journal Article | H72: YES | I72: EXCLUDE | J72: No eligible AI/ML system | K72: NO_RELEVANT_AI | L72: 46313 | M72: =IF(OR(I72="INCLUDE",I72="UNCERTAIN"),"RETRIEVE",IF(I72="EXCLUDE","EXCLUDE",""))
A73: 70 | B73: LIB-03192 | C73: 2026 | D73: Integrating artificial intelligence across the bladder cancer continuum: progress, promise, and pitfalls. | E73: INTRODUCTION: Bladder cancer is a prevalent and costly malignancy, with persistent challenges in early detection, accurate staging, and personalized treatment planning. Artificial intelligence (AI) has emerged as a transformative tool with the potential to address these limitations across the bladder cancer continuum. AREAS COVERED: This review synthesizes findings from 49 studies selected through a comprehensive literature search of PubMed, MEDLINE, Embase, Scopus, and Google Scholar spanning 2005 to 2025. The included studies explore AI applications in cystoscopic lesion detection, radiologic staging using CT and MRI, histopathologic grading, molecular biomarker profiling, treatment response prediction, and survival prognostication. EXPERT OPINION: AI has demonstrated significant promise in enhancing diagnostic precision, reducing interobserver variability, and enabling individualized treatment strategies. However, widespread clinical adoption remains limited due to challenges in data quality, lack of multicenter validation, integration into electronic health records, and regulatory hurdles. Future research should prioritize explainable AI models, prospective validation, and demonstration of cost-effectiveness and survival benefits. With continued innovation and standardization, AI is poised to become an integral component of precision oncology in bladder cancer care. | F73: Expert review of anticancer therapy | G73: Journal Article; Review | H73: YES | I73: EXCLUDE | J73: Ineligible publication type | K73: NON_PRIMARY_PUBLICATION | L73: 46313 | M73: =IF(OR(I73="INCLUDE",I73="UNCERTAIN"),"RETRIEVE",IF(I73="EXCLUDE","EXCLUDE",""))
A74: 71 | B74: LIB-04159 | C74: 2026 | D74: Integration of AI-Based Synthetic CT Generation and Auto-Segmentation for CBCT-Guided Adaptive Radiotherapy in Prostate Cancer: A Feasibility Study. | E74: Background/Objectives: Adaptive radiotherapy (ART) is essential yet expensive in prostate cancer treatment. This study aims to preliminarily validate the feasibility of an integrated AI workflow for CBCT-guided adaptive radiotherapy in prostate cancer, and to provide a technical foundation for subsequent clinical translation. Methods: Planning CT and CBCT images from 120 patients were used for training and validation, while 21 patients were reserved for testing. A CycleGAN-ResNet generated synthetic CT (sCT) from CBCT, and an nnU-Net model performed auto-segmentation on the sCT. Image quality and segmentation accuracy were quantitatively assessed. The original plan was recalculated on sCT to evaluate actual dose delivery; if clinical constraints were unmet, adaptive re-optimization was performed, and plans were compared. Results: The total time per fraction in this study was approximately 19 ± 6 min, falling within the reported feasibility range for online ART. sCT image quality was significantly improved, making them suitable for subsequent auto-segmentation and treatment planning. The auto-segmentation technique substantially enhanced contouring efficiency, with the automatically generated contours requiring only minor modifications to meet clinical standards. In dosimetric analysis, the adaptive plans provided superior target coverage, CI, and HI. Compared with the actual dose delivered by the original plan, the adaptive plans yielded lower bladder V40 and lower rectal mean dose/V30/V40/V50. Conclusions: This study preliminarily validated the feasibility of an integrated AI workflow that concatenates CycleGAN-based sCT generation, nnU-Net-based auto-segmentation, and sCT-based adaptive plan re-optimization. Compared with conventional segmented studies, this integrated exploration facilitates a more comprehensive assessment of the potential value of AI technologies in CBCT-guided prostate cancer ART, offering a preliminary solution for promoting a cost-effective adaptive radiotherapy approach. | F74: Cancers | G74: Journal Article | H74: YES | I74: EXCLUDE | J74: Technical-only/no downstream clinical task | K74: TECHNICAL_ONLY | L74: 46313 | M74: =IF(OR(I74="INCLUDE",I74="UNCERTAIN"),"RETRIEVE",IF(I74="EXCLUDE","EXCLUDE",""))
A75: 72 | B75: LIB-04533 | C75: 2018 | D75: Leveraging Big Data analytics in processing free-text entries of personal goals among patients undergoing bladder cancer surgery | E75: Aims: As we begin to leverage Big Data in health care settings and particularly in assessing patient-reported outcomes, we need novel analytics to address unique challenges. Latent Dirichlet Allocation (LDA) has been previously applied to extract themes from tetrabytes of free-text social media postings. In this study, LDA was applied to interview data collected as part of a prospective, longitudinal study of QOL in patients undergoing radical cystectomy and urinary diversion for bladder cancer (ClinicalTrials.gov NCT00745355). Methods: Patients' personal goals were collected using Ideographic QOL Interview probes: “For you to have the most satisfying life possible, what are the main things you want to accomplish?” “to solve?” “to prevent?” “keep the same?” “let go?” and “accept as they are now?”. Interviews were transcribed (N = 237; age 65 years, 19% female, and 63% college education) into free-text goal statements, e.g., “survive the surgery; have a manageable recovery process; return to a normal life after recovery.” (3093 statements altogether) LDA using Python scikit-learn Machine Learning tools extracted themes from baseline and 6 months post-surgery data separately to examine changes. Results: LDA summarized goal statements into clusters of words with common latent themes. Baseline themes included: “surgery operation life normal make healthy”, “cancer work pain live free living”, and “time family health friends traveling good”. At 6 months post-surgery, new themes emerged: “want continence issues good functioning money” and “cancer free family life know leakage”. Goals common in both time points changed in priority, shown in Fig. 1, that “time family health friends traveling good” became more salient post-surgery, while “surgery operation life normal make healthy” became less salient. Generally, patients' baseline goals were primarily on surgery success, recovery and a sense of normalcy thereafter. At post-surgery, however, priorities shifted to self-care and appreciation of life and family. Similar patterns of changes were found in other goal domains. Conclusions: Free-text data offer patients an important opportunity to voice their unique experiences toward improving outcomes. Thanks to novel Big Data analytics such as LDA, personal goals can be easily summarized in real time without the need for conventional fixed-length measures and qualitative data coding. (Figure Presented). | F75: Qual. Life Res. | G75: JOUR; Conference Abstract | H75: YES | I75: EXCLUDE | J75: Ineligible publication type | K75: CONFERENCE_ABSTRACT | L75: 46313 | M75: =IF(OR(I75="INCLUDE",I75="UNCERTAIN"),"RETRIEVE",IF(I75="EXCLUDE","EXCLUDE",""))
A76: 73 | B76: LIB-02788 | C76: 2025 | D76: Automated delineation of coronary arteries in radiotherapy planning CT using nnUnet based on data from RTOG 0617 and REQUITE trials | E76: Purpose/Objective: Irradiation of the heart substructures and mainly the coronary arteries is associated with higher mortality and increased risk of adverse events in patients receiving RT for lung cancer. We sought to develop an automated model to delineate critical heart substructures in non-contrast enhanced radiotherapy planning CTs. Open-source algorithms for automated coronary artery delineation on non-contrast enhanced CT (CECT) are sparse due to their small size, limited visibility and variable anatomical course. Material/Methods: Prospective RT-planning CT data from 221 planning CT-scans from patients receiving RT for lung cancer were randomly selected from the RTOG 06171 and the REQUITE3 trial. The CTs were almost equally collected from both. Manual delineation of left main (left), left circumflex (cflx) and left anterior descending (lad) coronary artery and correction was performed using 3D Slicer v5.6.0. Models were trained using 3D nnUnets v25. First, segmentations were created using platipy 2, a hybrid model, with geometric segmentation for coronary arteries. Generated segmentations were corrected manually and served as samples for training a first nnUNet Model (model 1). The following annotations were adjusted from model?s 1 output and used for training of model 2. This was repeated for models 3 and 4 with increasing patient numbers. To remove bias towards the model segmentations, 20 samples were manually completely annotated and used for final testing. Model performance was evaluated using the DICE coefficient. For more accurate evaluation of performance on small tubular structures, the 95th percentile Hausdorff-distace (HD95%) was calculated on the final test set. Performance on the final test set was compared to two publicly available models for coronary artery segmentation, the platipy model and the nnU-Net based STOPSTORM 4 model. Results: Performance was first evaluated on validation sets and improved with the rising number of training samples from models 1 to 3. In final testing, performance improved with rising training sample size (training samples, DICE, HD95%) from model 1, to model 2, to model 3 (n=80, 0.355, 7.935mm) with best performance in model 4 (n=100, 0.358, 7.773mm) (Table 1). Compared to both the platipy and STOPSTORM model, our model performance showed a significantly higher DICE (platipy = 0.0555, STOPSTORM = 0.2754) and lower HD95% (platipy = 15.7257mm, STOPSTORM= 17.7949mm) (Table 2). Conclusion: We have developed an automated segmentation model using an iterative approach, for segmenting coronary arteries in RT planning-CT, outperforming both platipy and the STOPSTORM model, despite only being trained on non-CECT.[Table presented] References: [1] Bradley J. D. et al. Data from RTOG 0617. published online 2018. doi:10.7937/tcia.2018.jze75u7v. [2] Finnegan, R. N. et al. Open-source, fully-automated hybrid cardiac substructure segmentation: development and optimisation. 2023 [3] Seibold P. et al. Requite:a prospective multicentre cohort study of patients undergoing radio-therapy for breast, lung or prostate cancer. Radiotherapy and oncology 138 (2019): 59-67. 2019. [4] van der Pol, L. et al. Auto-contouring of cardiac substructures for stereotactic arrhythmia radioablation (star): A stopstorm.eu consortium study. 2024 [5]Isensee, F. et al. “nnU-Net: a self-configuring method for deep learning-based biomedical image segmentation.” Nature methods 18.2 (2021): 203-211. | F76: Radiother. Oncol. | G76: JOUR; Conference Abstract | H76: YES | I76: EXCLUDE | J76: Ineligible publication type | K76: CONFERENCE_ABSTRACT | L76: 46313 | M76: =IF(OR(I76="INCLUDE",I76="UNCERTAIN"),"RETRIEVE",IF(I76="EXCLUDE","EXCLUDE",""))
A77: 74 | B77: LIB-00401 | C77: 2025 | D77: The Combined Role of FAPI PET and Liquid Biopsy in the Staging and Clinical Management of Bladder Cancer - FUTURE Trial | E77: The study will be a prospective two arms diagnostic phase II single‐center trial.Patients referred for diagnosis and treatment with diagnosis of bladder cancer, age > 18years, ECOG performance status < 2, ability to undergo an imaging study procedure will beconsidered for inclusion. For the study will be include 262 patients (118 and 144 in thearm 1 and 2, respectively).Eligible patients will sign the inform consent to be included in the study. Theparticipation to other clinical studies will be not, per se, an exclusion criterion.Before treatment, enrolled patients will be imaged by FAPI PET/CT and urine samples willbe collected and analyzed by Epicheck® test and Xpert® Bladder Cancer Detection.Thereafter, patients will be managed and treated according to international guidelinesand standard of care procedures in our institution. Safety will be recorded. Results ofFAPI imaging, Epicheck® test, and Xpert® Bladder Cancer Detection will be compared tostage, risk assessment groups as defined by currentguidelines, and clinical outcome.Diagnostic and predictive performances of FAPI imaging and liquid biopsy will be assessedand compared by using machine learning approaches. | F77: https://clinicaltrials.gov/study/NCT07257718 | G77: JOUR; Trial registry record | H77: YES | I77: EXCLUDE | J77: Protocol/no results | K77: PROTOCOL_NO_RESULTS | L77: 46313 | M77: =IF(OR(I77="INCLUDE",I77="UNCERTAIN"),"RETRIEVE",IF(I77="EXCLUDE","EXCLUDE",""))
A78: 75 | B78: LIB-01998 | C78: 2024 | D78: Prediction of extracapsular extension of prostate cancer by MRI radiomic signature: a systematic review. | E78: UNLABELLED: The objective of this review is to survey radiomics signatures for detecting pathological extracapsular extension (pECE) on magnetic resonance imaging (MRI) in patients with prostate cancer (PCa) who underwent prostatectomy. Scientific Literature databases were used to search studies published from January 2007 to October 2023. All studies related to PCa MRI staging and using radiomics signatures to detect pECE after prostatectomy were included. Systematic review was performed according to Preferred Reporting Items for Systematic Review and Meta-analyses (PRISMA). The risk of bias and certainty of the evidence was assessed using QUADAS-2 and the radiomics quality score. From 1247 article titles screened, 16 reports were assessed for eligibility, and 11 studies were included in this systematic review. All used a retrospective study design and most of them used 3 T MRI. Only two studies were performed in more than one institution. The highest AUC of a model using only radiomics features was 0.85, for the test validation. The AUC for best model performance (radiomics associated with clinical/semantic features) varied from 0.72-0.92 and 0.69-0.89 for the training and validation group, respectively. Combined models performed better than radiomics signatures alone for detecting ECE. Most of the studies showed a low to medium risk of bias. After thorough analysis, we found no strong evidence supporting the clinical use of radiomics signatures for identifying extracapsular extension (ECE) in pre-surgery PCa patients. Future studies should adopt prospective multicentre approaches using large public datasets and combined models for detecting ECE. CRITICAL RELEVANT STATEMENT: The use of radiomics algorithms, with clinical and AI integration, in predicting extracapsular extension, could lead to the development of more accurate predictive models, which could help improve surgical planning and lead to better outcomes for prostate cancer patients. PROTOCOL OF SYSTEMATIC REVIEW REGISTRATION: PROSPERO CRD42021272088. Published: https://doi.org/10.1136/bmjopen-2021-052342 . KEY POINTS: Radiomics can extract diagnostic features from MRI to enhance prostate cancer diagnosis performance. The combined models performed better than radiomics signatures alone for detecting extracapsular extension. Radiomics are not yet reliable for extracapsular detection in PCa patients. | F78: Insights into imaging | G78: Journal Article; Review | H78: YES | I78: EXCLUDE | J78: Ineligible publication type | K78: NON_PRIMARY_PUBLICATION | L78: 46313 | M78: =IF(OR(I78="INCLUDE",I78="UNCERTAIN"),"RETRIEVE",IF(I78="EXCLUDE","EXCLUDE",""))
A79: 76 | B79: LIB-04040 | C79: 2026 | D79: Real-time artificial intelligence prediction of peptide characteristics and MSFragger search improves multiplexed quantification of non-canonical HLA presented peptides in clear cell renal cell carcinoma | E79: Non-canonical HLA-presented peptides are promising therapeutic targets, but their low abundance makes them difficult to reproducibly identify and quantify, particularly in multiplexed immunopeptidomics workflows. Here we present MIRA-MS (Model-Informed Real-time Acquisition for Mass Spectrometry), a real-time acquisition strategy that combines fragment ion-indexed database searching with artificial intelligence-based prediction of peptide fragmentation and retention time to guide quantitative scan acquisition. In a clear cell renal cell carcinoma model, MIRA-MS increased the number of quantified non-canonical immunopeptides by 97-107% relative to standard acquisition methods while also improving recovery of canonical peptides by 45-89%. These results establish real-time AI-guided acquisition as a powerful approach for deeper and more reproducible immunopeptidome profiling. | F79: bioRxiv | G79: GEN; Preprint | H79: YES | I79: EXCLUDE | J79: Ineligible publication type | K79: PREPRINT_ONLY | L79: 46313 | M79: =IF(OR(I79="INCLUDE",I79="UNCERTAIN"),"RETRIEVE",IF(I79="EXCLUDE","EXCLUDE",""))
A80: 77 | B80: LIB-04118 | C80: 2026 | D80: Artificial intelligence in prostate biopsy: diagnostic applications, risk stratification, and precision oncology. | E80: Prostate biopsy remains the cornerstone for the diagnosis, risk stratification, and management of prostate cancer. However, biopsy interpretation is challenged by sampling limitations, tumor heterogeneity, and interobserver variability in Gleason grading. Recent advances in digital pathology and artificial intelligence (AI) have created new opportunities to improve diagnostic accuracy, reproducibility, and clinical decision-making. This narrative mini-review summarizes current evidence regarding AI applications in prostate biopsy evaluation. Relevant studies published between 2015 and 2026 were reviewed, focusing on AI-assisted cancer detection, automated Gleason grading, quantitative pathology, prognostic assessment, and multimodal approaches integrating histopathological, molecular, and clinical data. AI-based systems have demonstrated high accuracy in prostate cancer detection, Gleason pattern classification, and tumor burden assessment, with several studies showing strong concordance with expert genitourinary pathologists. These technologies have the potential to improve diagnostic consistency, enhance workflow efficiency, refine risk stratification, and support treatment planning. Emerging multimodal AI models integrating histopathological, genomic, imaging, and clinical information may further improve prognostic assessment and facilitate precision oncology approaches. However, challenges remain, including limited prospective validation, data heterogeneity, regulatory considerations, model interpretability, and integration into routine clinical workflows. AI is emerging as a valuable adjunct in prostate biopsy evaluation, with the potential to enhance diagnostic precision, grading reproducibility, and personalized patient management. Continued multicenter validation, development of explainable AI frameworks, and effective integration into multidisciplinary prostate cancer care pathways will be essential for successful clinical adoption and improved patient outcomes. | F80: Frontiers in oncology | G80: Journal Article; Review | H80: YES | I80: EXCLUDE | J80: Ineligible publication type | K80: NON_PRIMARY_PUBLICATION | L80: 46313 | M80: =IF(OR(I80="INCLUDE",I80="UNCERTAIN"),"RETRIEVE",IF(I80="EXCLUDE","EXCLUDE",""))
A81: 78 | B81: LIB-03555 | C81: 2026 | D81: Diagnostic assessment of artificial intelligence reconstruction on accelerated prostate MRI: a retrospective, paired, multi-reader multi-case study. | E81: OBJECTIVES: To determine whether AI-reconstructed prostate MRI at reduced acquisition times maintains prostate cancer (PCa) detection performance comparable to conventional scans. MATERIALS AND METHODS: This multicenter, retrospective, consecutive-cohort study included 120 multi-coil T2-weighted prostate MRI scans from the University Medical Center Groningen (UMCG) and 312 publicly available scans from New York University (NYU). An AI model trained on the NYU data was tested on retrospectively undersampled UMCG scans at acceleration factors R = 3 and R = 6 (i.e., data reduction in k-space). Eight experienced radiologists participated in a multi-reader multi-case PCa detection study. Diagnostic performance was assessed using the area under the receiver operating characteristic curve (AUROC). Histopathology and PI-RADS ≤ 2 findings served as reference standards. Multiple image quality metrics were subjectively evaluated using a 4-point Likert scale. RESULTS: No statistically significant reduction in PCa detection was observed at an MRI acceleration up to R = 6 (p = 0.08). AUROC values were 0.86 (95% CI: 0.74-0.90) for R = 1, 0.82 (0.72-0.88) for R = 3, and 0.80 (0.70-0.86) for R = 6. Compared to R = 1, R = 3 scans were rated by radiologists to have significantly improved sharpness (+0.2, p < 0.05) and lower noise (+0.1, p < 0.05). Overall visual quality at R = 6 remained comparable to R = 1 (2.81 at R6 vs. 2.74 at R1). CONCLUSION: AI-driven reconstruction enabled a sixfold acceleration of T2-weighted prostate MRI (0:33-1:27 min) without a statistically significant reduction in PCa detection, while preserving perceived image quality. However, the decreasing diagnostic performance at higher accelerations warrants further prospective evaluation. KEY POINTS: Question This study investigated whether deep learning reconstruction enables three- to sixfold acceleration without reducing radiologists' detection of clinically significant prostate cancer. Findings In a multi-reader multi-case study with eight radiologists, three- and sixfold acceleration showed no significant change in area under the receiver operating characteristic curve. Clinical relevance Deep learning reconstruction shortened T2-weighted acquisition times at sixfold acceleration while preserving perceived image quality and diagnostic performance across acceleration factors. | F81: European radiology | G81: Journal Article; Multicenter Study | H81: YES | I81: EXCLUDE | J81: Retrospective-only/ineligible design | K81: RETROSPECTIVE_ONLY | L81: 46313 | M81: =IF(OR(I81="INCLUDE",I81="UNCERTAIN"),"RETRIEVE",IF(I81="EXCLUDE","EXCLUDE",""))
A82: 79 | B82: LIB-03684 | C82: 2026 | D82: Predictive models for prostate cancer in patients with prostate-specific antigen levels in the gray zone using machine learning: a multi-center study | E82: Objective: This study aimed to develop, validate, and compare robust machine learning (ML) models that integrate readily available clinical data for predicting prostate cancer (PCa) and clinically significant PCa (csPCa) in patients within the prostate-specific antigen (PSA) gray zone from a multicenter cohort in Saudi Arabia. Methods: A retrospective multicenter study was conducted using data from 704 patients in Riyadh, Saudi Arabia. Two predictive models were developed: Model 1 for any PCa (N = 240/704) and Model 2 for csPCa (N = 154/704) patients. The input features included age, PSA density, prostate volume, and mpMRI risk. The dataset was split into training (N = 563) and testing (N = 141) sets. To ensure a robust evaluation, k-fold cross-validation (k = 5) was performed on the training set to assess model stability before the final evaluation on the independent test set. Eight ML algorithms were evaluated, with performance assessed using Accuracy, F1-score, and the Area Under the Receiver Operating Characteristic Curve (AUC) on the test set. Results: For clinically relevant Model 2 (csPCa prediction), the GradientBoost classifier demonstrated superior performance, achieving an AUC of 0.88 (95% CI: 0.83–0.93) and an accuracy of 0.82. For Model 1 (any PCa), GradientBoost also performed best, with an AUC of 0.897 and an accuracy of 0.83. Analysis of importance revealed that prostate volume was the most influential predictor in both models. Explainable AI (XAI) techniques, specifically SHAP (SHapley Additive exPlanations), were incorporated to provide transparency into the model’s decision-making process. Conclusion: The developed machine learning model, particularly the GradientBoost classifier, is a promising tool for risk stratification of csPCa in the PSA gray zone. This model has the potential to aid in patient selection for prostate biopsy, thereby reducing unnecessary procedures and associated morbidity in the Saudi population. Further prospective validation is required to confirm its clinical impact. Integrating this model into clinical software could offer clinicians real-time, data-driven risk assessments, thereby optimizing personalized patient care. © The Author(s) 2026. | F82: African Journal of Urology | G82: JOUR; Article | H82: YES | I82: EXCLUDE | J82: Retrospective-only/ineligible design | K82: RETROSPECTIVE_ONLY | L82: 46313 | M82: =IF(OR(I82="INCLUDE",I82="UNCERTAIN"),"RETRIEVE",IF(I82="EXCLUDE","EXCLUDE",""))
... A101: 98 | B101: LIB-03121 | C101: 2026 | D101: Clinical and MRI variables in decision support systems for prostate MRI: A systematic review of decision support tools, nomograms, and risk models | E101: Introduction: Workforce shortages and rising demand for MRI have increased interest in clinical decision support systems (CDSSs) to standardise imaging workflows. The Prostate Imaging–Reporting and Data System (PI-RADS) committee recommends real-time radiologist input to guide MRI pathways, but workforce constraints may limit consistent implementation. This systematic review examined CDSSs used in prostate MRI, including decision tools, nomograms, and risk calculators, to identify the clinical and MRI-derived variables they incorporate and assess their relevance for future development. Methods: A systematic search of Medline, Cochrane, CINAHL, Web of Science, and ProQuest was conducted in June 2025. Eligible studies were original research published in English since January 2015 describing development, validation, or clinical use of a CDSS using structured clinical and MRI-derived variables for prostate cancer diagnosis, pre-biopsy risk stratification, or staging. Exclusion criteria included radiomics-only studies, non-primary research, studies without MRI variables, and those lacking external validation. Two reviewers independently screened studies, extracted data, and assessed risk of bias using PROBAST. Certainty of evidence was appraised using the GRADE framework. Results: Twenty-two studies met inclusion criteria: fifteen evaluated nomograms, five described risk calculators, and two reported predictive models. None assessed a fully implemented CDSS. Common predictors included PI-RADS (82 %), prostate-specific antigen density (64 %), age (64 %), prostate-specific antigen (41 %), and prostate volume (23 %). Most tools showed strong discriminative accuracy (AUC >0.80), though calibration and decision curve analysis were inconsistently reported. Conclusion: Validated clinical and MRI predictors support robust CDSSs, but heterogeneity and lack of implementation limit evidence. Prospective multicentre validation is needed. Implications for practice: Radiographer-facing tools integrating key predictors could guide contrast use, staging, and workflow decisions, improve diagnostic accuracy and reduce unnecessary contrast administration. | F101: Radiography | G101: JOUR; Review | H101: YES | I101: EXCLUDE | J101: Ineligible publication type | K101: NON_PRIMARY_PUBLICATION | L101: 46313 | M101: =IF(OR(I101="INCLUDE",I101="UNCERTAIN"),"RETRIEVE",IF(I101="EXCLUDE","EXCLUDE",""))
A102: 99 | B102: LIB-02772 | C102: 2025 | D102: Clinical advantages in providing artificial intelligence-assisted prostate cancer diagnosis: A pilot study | E102: Prostate cancer is a prevalent male malignancy, with increasing incidence rates placing significant diagnostic burdens on pathology services worldwide. Artificial intelligence (AI) is emerging as a promising aid in enhancing diagnostic efficiency and accuracy. This study evaluates the clinical benefits of AI-assisted prostate biopsy (PB) diagnosis, with Paige Prostate tool, compared to non-AI-assisted PB diagnosis, focusing on its predictive accuracy for features in radical prostatectomy (RP) specimens. A retrospective analysis included 55 patients divided into two cohorts: one with non-AI-assisted PB diagnosis (n = 25) and another with AI-assisted PB diagnosis (n = 30). Pathological assessments recorded tumor size, Gleason score, Grade Group, and perineural invasion. The correlation between PB and RP results was analyzed, with statistical significance set at p < 0.05. AI-assisted PB diagnosis showed faster reporting times by 24 hours, enhancing workflow efficiency. AI assistance improved the correlation of tumor size between PB and RP, showing a substantial agreement (R=0.646, p < 0.001) compared to non-AI (R=0.479, p = 0.015). Gleason Score concordance increased by 13 % in the AI-assisted group, achieving 73.3 % versus 60 % in the non-AI-assisted group. This small pilot study suggests that AI-assisted PB diagnosis appears to enhance efficiency and accuracy in the diagnosis of prostate cancer, a finding to be confirmed with further studies. | F102: Pathol. Res. Pract. | G102: JOUR; Article | H102: YES | I102: UNCERTAIN | L102: 46313 | M102: =IF(OR(I102="INCLUDE",I102="UNCERTAIN"),"RETRIEVE",IF(I102="EXCLUDE","EXCLUDE",""))
A103: 100 | B103: LIB-04944 | C103: 2021 | D103: Delta radiomics: a systematic review. | E103: BACKGROUND: Radiomics can provide quantitative features from medical imaging that can be correlated with various biological features and clinical endpoints. Delta radiomics, on the other hand, consists in the analysis of feature variation at different acquisition time points, usually before and after therapy. The aim of this study was to provide a systematic review of the different delta radiomics approaches. METHODS: Eligible articles were searched in Embase, PubMed, and ScienceDirect using a search string that included free text and/or Medical Subject Headings (MeSH) with three key search terms: "radiomics", "texture", and "delta". Studies were analysed using QUADAS-2 and the RQS tool. RESULTS: Forty-eight studies were finally included. The studies were divided into preclinical/methodological (five studies, 10.4%); rectal cancer (six studies, 12.5%); lung cancer (twelve studies, 25%); sarcoma (five studies, 10.4%); prostate cancer (three studies, 6.3%), head and neck cancer (six studies, 12.5%); gastrointestinal malignancies excluding rectum (seven studies, 14.6%), and other disease sites (four studies, 8.3%). The median RQS of all studies was 25% (mean 21% ± 12%), with 13 studies (30.2%) achieving a quality score < 10% and 22 studies (51.2%) < 25%. CONCLUSIONS: Delta radiomics shows potential benefit for several clinical endpoints in oncology (differential diagnosis, prognosis and prediction of treatment response, and evaluation of side effects). Nevertheless, the studies included in this systematic review suffer from the bias of overall low quality, so that the conclusions are currently heterogeneous, not robust, and not replicable. Further research with prospective and multicentre studies is needed for the clinical validation of delta radiomics approaches. | F103: La Radiologia medica | G103: Journal Article; Systematic Review | H103: YES | I103: EXCLUDE | J103: Ineligible publication type | K103: NON_PRIMARY_PUBLICATION | L103: 46313 | M103: =IF(OR(I103="INCLUDE",I103="UNCERTAIN"),"RETRIEVE",IF(I103="EXCLUDE","EXCLUDE",""))
A104: 101 | B104: LIB-05581 | C104: 2025 | D104: EORTC GUCG 2418: “Strategies for Treatment Adaptation following Re-evaluation of the Bladder after using pRimary neoadjuvant Systemic Therapies” (STARBURST-1): an EORTC platform trial | E104: Introduction and objectives The standard treatment for patient with muscleinvasive bladder cancer (MIBC) consists of neoadjuvant systemic therapy (NAT) followed by radical cystectomy (RC) or trimodal therapy (TMT). Currently, patients are not routinely reassessed after NAT and proceed directly to local treatment, leading to a missed opportunity for patients with complete or near complete response to benefit from bladder sparing strategies. On the other hand, for the nonresponders, it is a missed opportunity for escalation strategy with systemic treatment. Unfortunately, several studies have shown an insufficient concordance between the clinical and pathological staging of MIBC, unraveling the inadequacy of the current methods for clinical staging post-NAT. The STARBURST project aims to refine the bladder cancer treatment landscape in two successive steps. First, SB-1 study aims to develop and validate a clinical multimodal signature to enhance the prediction of the systemic treatment response. Second, SB-2 will be developed as a risk-adapted strategies trial based on the response post NAT. Here below, we present the methodology of SB-1. Methods SB-1 is a prospective, phase II, single arm cohort of 237 patients with newly diagnosed MIBC (pT2-pT4a N0-1 M0). • All patients will be treated with standard of care NAT followed by RC. • All patients will be assessed before NAT by a cystoscopy, urine cytology, bladder multiparametric MRI (mpMRI) (Vi-RADS score), blood and urine samples (ctDNA,utDNA and multiplex urine molecular biomarkers). • After completing the NAT, every patient will be reassessed by a cystoscopy (+/-biopsy), a bladder mpMRI (NAcVI-RADS score) and by urinary and blood markers. The primary endpoints of SB-1 is to prospectively validate: • The accuracy of the NacVI-RADS score to predict the pathological complete or near complete response defined as the absence of residual disease or the absence of muscle invasive disease on the cystectomy specimen (ypT0 or ypTa/1) • To predict the absence of muscle invasive disease (ypT2 vs ypT0/a/1) assessed by the negative predictive value (NPV), the positive predictive value (PPV) and the receiver operating curves (ROC). Secondary endpoints include the assessment of new biomarkers including blood circulating tumor DNA (ctDNA) and urine tumor DNA (utDNA), urines multiplex biomarkers, pathomics, radiomics and molecular alterations that could predict the pathological response. Conclusions The EORTC GUCG 2418 STARBURST-1 project offers a unique opportunity to define and validate a clinical multimodal signature of response to NAT properly and further offer patients downstream risk-adapted strategies. NCT02834884. | F104: Asia-Pac. J. Clin. Oncol. | G104: JOUR; Conference Abstract | H104: YES | I104: EXCLUDE | J104: Ineligible publication type | K104: CONFERENCE_ABSTRACT | L104: 46313 | M104: =IF(OR(I104="INCLUDE",I104="UNCERTAIN"),"RETRIEVE",IF(I104="EXCLUDE","EXCLUDE",""))
A105: 102 | B105: LIB-00364 | C105: 2025 | D105: Robotic Prostatectomy Artificial Intelligence Low Pressure Pain (RALP) Trial | E105: In this trial, 100 patients undergoing robotic prostatectomies will be randomised to haveeither the AIRSEAL® Insufflation System (AIS) or the Stryker PneumoClear Insufflatordevices used to maintain pneumoperitoneum during surgery. Data relating tointra‐operative and post‐operative pain will be collected. This data will be used toidentify any differences in outcomes between the two arms of the trial.The main aim of this feasibility study will be to inform the feasibility and design of asubsequent definitive full‐scale trial. The feasibility trial will collect data aboutrecruitment, study conduct, and assessment methods. The objectives of the feasibility areto ‐ Assess recruitment rates ‐ Evaluate whether the study can run in line with the study protocol ‐ Identify the feasibility of collecting clinical data ‐ Evaluate treatment‐based adverse events, serious adverse events, anticipated adversedevice effects, unanticipated adverse device effects and all device deficiencies anduse errors, regardless of relationship to an adverse event ‐ Estimate the likely magnitude of the effect of the intervention. To allow forestimation of the sample size for the full trialThe subsequent large scale, multi‐center trial following this feasibility trial willfocus on severity of pain during and immediately after surgery in the recovery room andthen by 6‐hour increments, measured by a 0 ‐ 10 Numeric Rating Scale (NRS) and a PMD‐200nociception non‐invasive monitor as the primary outcomeSecondary outcomes include:Pre‐Operative 1. Pre‐op vitals including height and weight 2. Pre‐op labsIntra‐operative 1. Insufflation Pressure 2. Estimated blood loss 3. Blood transfusion (intra‐operative) 4. Procedure time (initial incision to closure) 5. Surgeon‐determined need to increase IAP beyond "study pressure" 6. Administration of transversus abdominis plane block 7. Urine output 8. Anesthetic/pain medication administration 9. MedaSense PMD‐200 monitor for pain documentation 10. Intraoperative Peak Airway Pressure every 15 minutes 11. Intraoperative End Tidal Carbon Dioxide (ETCO2) every 15 minutesPost‐Operative During hospital discharge, all subjects will be evaluated for incidenceand severity of pain using a 0‐10 numeric rating scale (NRS) and records of medicationuse and a PMD‐200 monitor. These data will be captured in the Case Report Forms.Recovery room: 1. Time in recovery room 2. Post‐op pain incidence and severity (abdominal) NRS 3. Pain medications 4. Post‐ op labs (CBC, Chem‐7) per standard of care 5. Vital signs 24 hrDischarge: 1. Post‐op pain incidence and severity (abdominal) NRS 2. Presence or absence of postoperative nausea or vomiting 3. Pain medications 4. Length of hospital stay 5. Pain Interference and Pain Intensity short form surveys 6. Any complications that were observed. Post‐operative complications through 30 days,reported using Clavien‐Dindo Classification, including 30‐day mortality 7. Return to operating room within 24 hour 8. Readmission to hospital within 30 daysClassification, including 30‐day mortalityAll Adverse Events (intra‐operative and post‐operative through 30 days): 1. Adverse Events 2. Serious Adverse Events 3. Anticipated Adverse Device Effects 4. Unanticipated Adverse Device Effects 5 All device deficiencies and use errors,regardless of relationship to an adverse eventPatients under the care of the urology department at the Lister Hospital, Stevenage willbe listed in clinic for a robotic prostatectomy. If patients meet the eligibilitycriteria for the trial, they will be approached and informed of the RALP clinical trialduring their clinic consultation, by a member of the clinical team (likely a urologicalconsultant).Patients will be provided with a patient information sheet informing them of the aims andmethodology of the trial. Members of the research department will be able to answer anyoutstanding questions patients might have.Written informed consent will be obtained from eligible patients (n=40) willing toparticipate in the trial. If patients consent, their GP will subsequently be written toand informed of their involvement in the trial.Pre‐Operative data collection:Within 30 days of a subject's scheduled procedure, members of the research department atLister hospital will obtain a medical history and record the subject's demographic (age,race, sex and date of birth) and baseline information (height, weight, andsystolic/diastolic blood pressure). Within 30 days prior to the planned procedure date,obtain serum blood tests per standard of care. These will typically include:• FBC • Renal function test • CRP This data, along with all subsequent trial related datawill be anonymised and subsequently inputted into a database created by the Centre forHealth Services and Clinical Research at the University of Hertfordshire.Preoperative Randomization:Randomization will be done electronically via a database which is facilitated by theUniversity of Hertfordshire. Patients will be randomized 1:1 to either AIS (at 8 mmHg) orStryker PneumoClear Insufflator Arm 1: AIRSEAL® Insufflation System (AIS) ‐ 8 mmHg Arm 2:Stryker PneumoClear Insufflator ‐ 8 mmHg.Methods and Procedure:Patients will undergo their robotic assisted prostatectomy with the use of either theAIRSEAL® Insufflation System (AIS) or Stryker PneumoClear Insufflator depending on whicharm of the trial they have been randomized to. Patients will be blinded to theintervention (AIRSEAL® Insufflation System (AIS) or Stryker PneumoClear Insufflator).Both systems are commonly used devices across many NHS trusts and there is currently noevidence comparing patient outcomes between use of the two devices.This study will be conducted at one site by one surgeon performing 40 total procedures.Study subjects will be prepared for surgery per standard institutional policy andpractice. Standard operative procedures will be followed.Case Report Forms will be also be used to collect data relating to pre‐operative,intra‐operative and post‐operative outcomes. This data will relate to outcomes such asintra‐operative pain, post operative pain scores, medication use, duration of hospitalstay, presence of nausea or vomiting etc...The final patient follow up will be in a clinic appointment 30 days following theiroperation. Ongoing post‐operative outcomes will be assessed (pain scores, medication use,adverse events etc...).Data will be inputted on the database which is subsequently processed and statisticallyanalysed and reviewed. Differences in outcomes between the two arms of the trial may beidentified.Once the aforementioned data has been processed and reviewed, results may be publishedand also distributed to those trial participants who wished to receive ongoinginformation and results from the trial.The outcomes of this research will be used to inform future research such as a full scaletrial with a larger number of patients and larger volume of data | F105: https://clinicaltrials.gov/study/NCT06915909 | G105: JOUR; Trial registry record | H105: YES | I105: EXCLUDE | J105: Protocol/no results | K105: PROTOCOL_NO_RESULTS | L105: 46313 | M105: =IF(OR(I105="INCLUDE",I105="UNCERTAIN"),"RETRIEVE",IF(I105="EXCLUDE","EXCLUDE",""))
A106: 103 | B106: LIB-02398 | C106: 2024 | D106: Role of [18F]-PSMA-1007 PET radiomics for seminal vesicle invasion prediction in primary prostate cancer. | E106: PURPOSE: The purpose of this study is to investigate the diagnostic utility of [18F]-PSMA-1007 PET radiomics combined with machine learning methods to predict seminal vesicle invasion (SVI) after radical prostatectomy (RP) in prostate cancer (PCa) patients. METHODS: This is a post hoc retrospective analysis for a prospective clinical trial that included a consecutive sample of PCa patients (n = 140) who had [18F]-PSMA-1007 PET/CT prior to RP. The intraprostatic lesion's volume of interest (VOI) was semi-automatically sketched using a threshold of 40 % maximum standardized uptake value (SUVmax), namely 40%SUVmax-VOI, and seminal vesicle glands were manually contoured, namely SV-VOI. Models were built using a variety of machine learning methods such as logistic regression, random forest, and support vector machine. The area under the receiver operating characteristic curve (AUC) was calculated for different models, and the prediction performances of radiomics models were compared against the radiologists' assessment. Kaplan-Meier analysis was utilized to assess the effectiveness of selected radiomics features to determine the progression-free survival (PFS) probability. RESULTS: The training set had 112 patients and the test set had 28 patients. The highest AUC for the PET radiomics model of 40%SUVmax-VOI and the PET radiomics model of SV-VOI were 0.85 and 0.96 in the test set, respectively. The PET radiomics model of SV-VOI had a significantly higher AUC compared to the radiologists' assessment (P < 0.05). The Kaplan-Meier analysis showed that PET radiomics features were associated with PFS in patients with PCa. CONCLUSION: Radiomics models developed by preoperative [18F]-PSMA-1007 PET were proven useful in predicting SVI, and PSMA PET radiomics features were correlated with PFS, suggesting that the PSMA PET radiomics might be an accurate tool for PCa characterization. | F106: Computers in biology and medicine | G106: Journal Article; Research Support, Non-U.S. Gov't | H106: YES | I106: EXCLUDE | J106: Retrospective-only/ineligible design | K106: RETROSPECTIVE_ONLY | L106: 46313 | M106: =IF(OR(I106="INCLUDE",I106="UNCERTAIN"),"RETRIEVE",IF(I106="EXCLUDE","EXCLUDE",""))
A107: 104 | B107: LIB-03815 | C107: 2026 | D107: Explainable artificial intelligence in prostate cancer treatment recommendation: A decision support system for oncological expert panels. | E107: BACKGROUND: Therapeutic decisions in clinical oncology are commonly established through interdisciplinary consensus in multidisciplinary cancer conferences (MCC). Artificial intelligence (AI) may support these processes by generating data-driven treatment recommendations (TR). We developed and evaluated an explainable AI system designed to reproduce MCC-based treatment decisions for metastatic and non-metastatic prostate cancer (PC). METHODS: Clinical data from patients with histologically confirmed PC discussed in MCC between 2015 and 2022 were transformed into structured datasets. A hierarchical modeling framework was implemented to first predict overarching treatment categories and subsequently specify therapeutic strategies. Multiple machine learning and deep learning algorithms were trained to replicate MCC recommendations. Model performance was assessed using F1-scores. RESULTS: A total of 5478 MCC cases including 76 clinical input variables and 23 treatment output parameters were analyzed. The AI system generated automated TR with high predictive accuracy across both hierarchical levels. For high-level categories, F1-scores reached 0.89 for surgery and 0.81 for radiation therapy. For detailed recommendations, F1-scores reached 0.99 for prostatectomy and 0.98 for PSMA-ligand therapy. Lower performance in anti-cancer drug categories likely reflects smaller sample sizes. Feature importance analyses ensured model transparency and interpretability. CONCLUSION: To our knowledge, this study presents one of the first large-scale explainable AI system capable of generating MCC-aligned treatment recommendations for metastatic and non-metastatic PC within a multi-target framework. It incorporates the largest reported number of clinical input and treatment output parameters in this setting. Strong predictive performance and interpretability support its potential as a scalable decision-support tool in multidisciplinary oncology. Prospective validation is warranted. | F107: European journal of cancer (Oxford, England : 1990) | G107: Journal Article | H107: YES | I107: EXCLUDE | J107: Retrospective-only/ineligible design | K107: RETROSPECTIVE_ONLY | L107: 46313 | M107: =IF(OR(I107="INCLUDE",I107="UNCERTAIN"),"RETRIEVE",IF(I107="EXCLUDE","EXCLUDE",""))
A108: 105 | B108: LIB-03411 | C108: 2026 | D108: Postoperative Pancreatic Fistula After Pancreatoduodenectomy | E108: Objective: – Assess the potential added benefit of radiomics to clinical models for predicting postoperative pancreatic fistula (POPF) after pancreatoduodenectomy (PD). Summary of Background Data: – Radiomics extracts quantitative data from medical imaging based on enhancement patterns. Clinical applications of radiomics have been investigated in pancreas, lung, breast, and prostate cancers. Methods: – This single center retrospective study included all patients with available preoperative CT scan before PD from 2009-2021. Radiomic features that reflect heterogeneity in enhancement patterns were extracted from manually segmented future remnant pancreas. Clinical variables and radiomic features were used with random forest classifier to design five predictive models for grade B/C clinically relevant POPF (CR-POPF): preoperative (PreClin), intraoperative (IntraClin), radiomics alone (Rad), PreClin with radiomics (PreClin-Rad), and IntraClin with radiomics (IntraClin-Rad). Training data was randomly selected and comprised 70% (n=339) of the cohort, and the remaining 30% (n=145) was the test set. A prospective validation cohort (n=60) was also created. Results: – From 1855 eligible PD, all 234 with POPF were included, random sampling was used on the remainder to select 250 without POPF. In the test set, PreClin (AUC=0.74), IntraClin (AUC=0.78), and Rad (AUC=0.75) performed similarly. Best results were noted with combined models, AUC=0.82 for PreClin-Rad and AUC=0.84 for IntraClin-Rad. The same patterns were noted in the prospective validation cohort with PreClin-Rad performing best (AUC=0.78). Conclusion: – Radiomics compared favorably with clinical risk scores for CR-POPF after PD, and combined models with radiomics and clinical data offer the strongest prediction. The PreClin-Rad model demonstrates the greatest clinical utility with excellent predictive outcomes relying entirely on preoperative data in the test and prospective validation cohorts. | F108: Ann. Surg. | G108: JOUR; Article | H108: YES | I108: EXCLUDE | J108: Wrong population | K108: WRONG_POPULATION | L108: 46313 | M108: =IF(OR(I108="INCLUDE",I108="UNCERTAIN"),"RETRIEVE",IF(I108="EXCLUDE","EXCLUDE",""))
A109: 106 | B109: LIB-05790 | C109: 2026 | D109: Deep learning-based CD8+ T cell inflammation model for predicting prognosis and combination of targeted and immunotherapy benefit from digital pathology in clear cell renal cell carcinoma | E109: Introduction & Objectives: Deep learning holds significant promise for improving clear cell renal cell carcinoma (ccRCC) diagnosis and treatment. However, studies concerning tumor microenvironment (TME) based on pathological images and artificial intelligence are very limited. Materials & Methods: We developed a deep learning-based CD8+ T cell inflammation signature (DL-CD8T) for ccRCC from Hematoxylin and eosin (H&E)-stained whole slide images (WSIs) through a clustering-constrained attention multiple-instance learning method. A total of 1151 patients with whole slide images, molecular immunophenotyping, and clinical data from four patient cohorts were retrospectively analyzed. Immunohistochemistry based on tissue microarray and single-cell RNA sequencing analysis were also performed to verified the specific TME of the DL-CD8T. Prediction performance of prognosis and combination of targeted and immunotherapy benefit was verified in four independent validation cohorts. Results: Based on a convolutional neural network, we developed the DL-CD8T for ccRCC in the training cohort (TCGA cohort), which could distinguish patients with higher level of CD8+ T cell inflammation through conventionally used H&E-stained whole slide image, with aera under the curve (AUC) of 0.781 (0.741-0.817, p< 0.0001). Verification of the DL-CD8T was also performed well in the independent CPTAC cohort, with AUC of 0.741 (0.599-0.853, p< 0.0001). Further verification indicated that when the cut-off value of DL-CD8T was set as “0.4699”, the prediction model achieved its best performance in predicting CD8+ T cell inflammation tumors, and patients with DL-CD8T higher than “0.4699” were grouped as DL-CD8T(+) group. DL-CD8T(+) was found to be significantly associated with high infiltration abundance of CD8+ T cell, higher expression levels of PD-1, PD-2, PD-L1, CTLA-4, TIM-3 and higher tumor mutation burden. Immunohistochemistry on formalin-fixed, paraffin-embedded tissue indicated that DL-CD8T(+) tumors were characterized by a high degree of CD8+ T cell infiltration. Single-cell RNA sequencing analysis also verified the specific tumor immune microenvironment for DL-CD8T(+). Furthermore, DL-CD8T could distinguish ccRCC patients with high survival risk, with hazard ratio of 1.693-3.591 in three independent patient cohorts. In addition, DL-CD8T could predict combination of targeted and immunotherapy benefit from digital pathology in ccRCC with hazard ratio of 0.265 (p=0.029), which could act as a biomarker for combination of targeted and immunotherapy. Conclusions: We developed and verified DL-CD8T for ccRCC, which could predict prognosis and targeted and immunotherapy benefit from digital pathology. Pending prospective validation, it may be used to improve risk stratification and inform personalized therapy. | F109: Eur. Urol. | G109: JOUR; Conference Abstract | H109: YES | I109: EXCLUDE | J109: Ineligible publication type | K109: CONFERENCE_ABSTRACT | L109: 46313 | M109: =IF(OR(I109="INCLUDE",I109="UNCERTAIN"),"RETRIEVE",IF(I109="EXCLUDE","EXCLUDE",""))
A110: 107 | B110: LIB-03899 | C110: 2026 | D110: Optimizing post-prostatectomy management: A machine learning tool to identify low-risk patients and minimize unnecessary burden in localized prostate cancer. | E110: Background: Biochemical recurrence (BCR) is a key early indicator of disease progression in localized prostate cancer (LPC). While uniform, intensive follow-up is standard, it leads to significant resource burden and patient anxiety, as patients particularly at minimal risk may not require it. It remains to be established whether machine learning models can provide efficient, data-driven decision-making solutions in this clinical context. Methods: This is a retrospective cohort study using structured electronic medical record data from a tertiary care center (West China Hospital). Eligible patients had clinical LPC and underwent RP between 2017-2024, with at least one year of follow-up. BCR was defined as PSA≥0.2 ng/mL with two consecutive increases post-RP. Predictors encompassed biopsy, pathological Gleason scores, prostate size, pT stage, surgical margin status, pre- and post-RP PSA levels, and inflammatory ratios. Random Forest (RF) and XGBoost models were developed with hyperparameter tuning via 10-fold cross-validation. Model performance was evaluated using 500 bootstrap resamples to obtain optimism-corrected Area Under Curve (AUC), Sensitivity, Specificity, PPV, NPV, and Calibration-In-The-Large (CITL). Clinical utility was assessed via Decision Curve Analysis (DCA) to guide follow-up decisions. Results: Among 763 male patients (mean age 67.3 years) in the cohort, 78 (10.2%) patients experienced BCR within 1 year (median 6 months). After bootstrap correction, the RF model achieved superior discrimination (optimism-corrected AUC: RF 0.90 vs. XGboost 0.82, P<0.05) and better calibration (CITL: RF -0.04 vs. XGboost 0.23, P<0.05). Both models demonstrated a consistently high NPV (0.97), supporting safe exclusion of low-risk patients from intensive surveillance. DCA revealed that using the RF model provided a superior net benefit across the risk thresholds of 0-54.2% compared to XGboost and default strategies of "follow-all" or "follow-none." A model-guided management strategy could reduce approximately 70% of health utilization cost per low-risk patient and reallocate about 19 clinician workdays to higher-value care annually. Conclusions: Using rigorous internal validation, we developed a highly discriminative and well-calibrated RF model capable of accurately identifying patients at minimal short-term BCR risk. The model's high NPV and demonstrated clinical utility suggest strong potential to safely de-escalate post-RP surveillance. Prospective multi-center validation is warranted to confirm its generalizability and its impact on clinical workflow and resource optimization. (Table Presented.) | F110: ASCO MEETING ABSTRACTS | G110: JOUR; Conference Abstract | H110: YES | I110: EXCLUDE | J110: Ineligible publication type | K110: CONFERENCE_ABSTRACT | L110: 46313 | M110: =IF(OR(I110="INCLUDE",I110="UNCERTAIN"),"RETRIEVE",IF(I110="EXCLUDE","EXCLUDE",""))
A111: 108 | B111: LIB-03174 | C111: 2025 | D111: Utilization of artificial intelligence in prostate cancer detection: a comprehensive review of innovations in screening and diagnosis. | E111: Prostate cancer management has long been challenged by the limitations of traditional screening tools like PSA testing, which contribute to significant rates of overdiagnosis and overtreatment. While advanced imaging such as multiparametric MRI (mpMRI) has improved the diagnostic pathway, the integration of Artificial Intelligence (AI) is now catalyzing a paradigm shift across the entire continuum of care. This comprehensive review details the transformative role of AI in prostate cancer. In diagnostics, deep learning algorithms enhance the interpretation of mpMRI by improving lesion detection, segmentation, and risk stratification, thereby reducing unnecessary biopsies. In digital pathology, AI provides automated and consistent Gleason grading, minimizing inter-observer variability and refining prognostication. In the therapeutic domain, AI is crucial for personalizing treatment by streamlining radiotherapy planning through automated contouring, predicting patient outcomes and toxicity, and enabling the development of adaptive therapy strategies for advanced disease. Multimodal AI models that synthesize imaging, biomarker, and clinical data are creating robust predictive tools for superior clinical decision support. Despite formidable challenges related to prospective validation, data equity, and regulatory approval, AI is paving the way for a new standard of care characterized by greater precision, efficiency, and personalization. | F111: Frontiers in immunology | G111: Journal Article; Review | H111: YES | I111: EXCLUDE | J111: Ineligible publication type | K111: NON_PRIMARY_PUBLICATION | L111: 46313 | M111: =IF(OR(I111="INCLUDE",I111="UNCERTAIN"),"RETRIEVE",IF(I111="EXCLUDE","EXCLUDE",""))
A112: 109 | B112: LIB-05576 | C112: 2025 | D112: DNA DAMAGE REPAIR FAMILY GENOMIC ALTERATIONS AS A PREDICTIVE BIOMARKER FOR RESPONSE TO IMMUNE CHECKPOINT INHIBITORS IN MULTIPLE CANCERS | E112: Background DNA damage repair (DDR) genes are a class of genes that play a significant role in the occurrence and drug resistance of tumor cells. Current research has shown that certain DDR genes are related to the efficacy of immunotherapy. However, the association between alterations in the DDR gene family in tumors and the response to immune checkpoint inhibitors still requires further investigation, for that prior studies have focused on either an individual gene or a predefined set of genes. Herein, this study aimed to evaluate the predictive potential of DDR gene mutations for treatment responses to immune checkpoint inhibitors across various cancers. By developing and validating DDR gene signatures, the research sought to establish biomarkers that could optimize therapeutic outcomes in immunotherapy. Methods The study utilized data from multiple independent cohorts, including patients treated with ICIs, collected via whole-exome sequencing and targeted sequencing. The analysis incorporated DDR gene mutations, tumor mutational burden, and clinical data. The research applied machine learning algorithms to create DDR-based biomarker signatures and validated their predictive accuracy across different cancer types. Furthermore, we incorporated single-nucleus RNA sequencing (snRNA-seq) and ATAC-seq data from a clear cell renal cell carcinoma cohort to investigate transcriptomic and epigenetic alterations associated with DDR mutations. Results Analyzing over 10,953 patient revealed that DDR gene mutations occurred in 36.75% of patients, with certain cancer types, including cutaneous melanoma, bladder cancer, and lung cancers, showing the highest mutation frequencies. DDR gene alterations were linked to significantly improved overall survival and progression-free survival in several cancers, particularly in patients receiving combined PD-1/CTLA-4 immunotherapy. A DDR signature of 34 genes was identified as a strong prognostic factor, showing enhanced immunotherapy responses. However, in cancer patients received ICIs, a threshold of two DDR mutations did not provide additional survival benefits compared to individual mutations. Immunotherapy-related DDR mutations were associated with elevated TMB and increased immune cell infiltration, suggesting enhanced anti-tumor immunity in tumor microenvironment. Conclusions The study highlights DDR gene alterations as reliable predictive biomarkers for ICI treatment responses, offering significant insights into personalized cancer therapies. It proposes the development of distinct DDR-based biomarkers for immunotherapy, emphasizing the clinical utility of these signatures in optimizing therapeutic strategies. The study underscores the need for prospective validation and further exploration of the underlying immunological mechanisms driving the observed clinical benefits. Additionally, it suggests that DDR mutation status could play a crucial role in enhancing immunotherapy outcomes across multiple malignancies. | F112: J. Immunother. Cancer | G112: JOUR; Conference Abstract | H112: YES | I112: EXCLUDE | J112: Ineligible publication type | K112: CONFERENCE_ABSTRACT | L112: 46313 | M112: =IF(OR(I112="INCLUDE",I112="UNCERTAIN"),"RETRIEVE",IF(I112="EXCLUDE","EXCLUDE",""))
A113: 110 | B113: LIB-05753 | C113: 2026 | D113: 41st Annual EAU Congress | E113: The proceedings contain 1923 papers. The topics discussed include: CT radiomics and AI for differentiating oncocytoma from renal cell carcinoma; mechanism of obesity induced ACSM5 deficiency promoting calcium oxalate induced renal tubular epithelial cell injury; recurrence-free survival after checklist adoption in non-muscle invasive bladder cancer: insights from a single-center experience; de novo lower urinary tract symptoms after robot assisted radical prostatectomy: evaluation of incidence and risk factors; prostatic fluid DNA methylation biomarkers enable high-accuracy prostate cancer diagnosis: a prospective pilot study; a phase 1 safety, PK and preliminary efficacy study of localized therapy using Enolen® (enzalutamide) implants for early-stage prostate cancer; incidence and outcomes of non-visualization during dynamic sentinel lymph node biopsies for penile cancer: a contemporary high volume center retrospective analysis; utilization of biomarkers to guide biopsy decisions for PI-RADS 3 prostate lesions; bladder preservation in patients with muscle-invasive bladder cancer who refused/unwilling to radical cystectomy after complete response to neoadjuvant systemic and local (chemo/immune) therapy. a 24-years single center experience; and transurethral injection of autologous muscle precursor cells in collagen solution for the treatment of female stress urinary incontinence – results from a blinded, prospective and randomized phase ii clinical trial (SUISSE MPC2 Study). | F113: Eur. Urol. | G113: JOUR; Conference Review | H113: YES | I113: EXCLUDE | J113: Ineligible publication type | K113: CONFERENCE_ABSTRACT | L113: 46313 | M113: =IF(OR(I113="INCLUDE",I113="UNCERTAIN"),"RETRIEVE",IF(I113="EXCLUDE","EXCLUDE",""))
A114: 111 | B114: LIB-03162 | C114: 2026 | D114: Artificial intelligence and multi-omics integration in liquid biopsy for genitourinary cancers: a systematic scoping review. | E114: BACKGROUND: Liquid biopsy, combined with multi-omics profiling and artificial intelligence (AI), offers a minimally invasive strategy for cancer detection, monitoring, and prognostication. Evidence in genitourinary (GU) cancers remains fragmented across analytes, biofluids, and computational approaches, limiting clinical translation. OBJECTIVE: To map and synthesize AI-enabled liquid biopsy research in GU cancers and identify methodological and clinical gaps. METHODS: A systematic scoping review was conducted following PRISMA-ScR and JBI guidelines (protocol registered in PROSPERO: CRD420251137304). Comprehensive searches of MEDLINE, Embase, Scopus, Web of Science, Cochrane Library, IEEE Xplore, preprint servers, and major conference proceedings identified eligible studies published 1 January 2018-1 August 2025. Dual independent screening and data charting were performed. Note on performance metrics: reported AUC, sensitivity, and specificity values were extracted verbatim from included studies and from previously published meta-analyses when cited; this review did not perform a de-novo quantitative meta-analysis or statistical pooling of primary study results. RESULTS: A total of 115 studies were included, spanning biomarker discovery, algorithm development, and early translational efforts. Urinary exosome diagnostics in urothelial cancer have been reported in prior meta-analyses to show pooled AUC ≈ 0.83 (sensitivity ≈ 75%, specificity ≈ 77%); these pooled estimates were cited but not recalculated in the present scoping review. ctDNA-based approaches showed strong prognostic value in advanced prostate cancer, with detection rates consistently > 60%. Testicular germ cell tumor research remains dominated by miR-371a-3p studies, with limited AI or multi-omics integration. Intermediate-fusion and graph-based models offered advantages over simple concatenation but were hindered by small sample sizes, batch effects, and lack of external validation. CONCLUSION: AI-driven multi-omics liquid biopsy holds promise for GU oncology but is constrained by fragmented evidence and methodological variability. Future research should prioritize standardized pipelines, multi-center validation, prospective trials, and explainable AI to accelerate clinical translation. | F114: International urology and nephrology | G114: Journal Article; Scoping Review | H114: YES | I114: EXCLUDE | J114: Ineligible publication type | K114: NON_PRIMARY_PUBLICATION | L114: 46313 | M114: =IF(OR(I114="INCLUDE",I114="UNCERTAIN"),"RETRIEVE",IF(I114="EXCLUDE","EXCLUDE",""))
... A158: 155 | B158: LIB-01416 | C158: 2023 | D158: Machine learning algorithm to define optimal candidates for active surveillance in intermediate-risk prostate cancer | E158: Introduction & Objectives: The eligibility of intermediate-risk (IR) prostate cancer (PCa) patients for active surveillance (AS) is limited by very strict consensus-based inclusion criteria and lack of data from large prospective cohorts. Many patients outside of these criteria may possess low absolute risks of local or distant progression. The aim was to develop new selection criteria for AS in IR patients, and to compare them to the currently recommended inclusion criteria. Materials & Methods: Retrospective study including patients from 14 European referral centers who underwent pre-biopsy mpMRI, image-guided biopsies and radical prostatectomy. The cohort included biopsy-naive IR PCa patients who met the following inclusion criteria: Gleason Grade Group (GGG) 1-2 on combined image-guided biopsies, PSA <20 ng/mL, and cT1-cT2 tumors. The histological endpoints were adverse pathological features, defined as non-organ-confined disease (i.e., ≥pT3a) and/or lymph node involvement (i.e., pN+) and/or GGG ≥3 at final pathology. We relied on automated chi-squared interaction detection (CHAID); a recursive machine learning partitioning algorithm developed to predict adverse pathological features. Results: A total of 594 patients with IR PCa were included, of whom 220 (37%) had adverse features at final pathology. PI-RADS score (weight: 0.726/1), PSA density (weight: 0.158/1), and clinical T stage (weight: 0.116/1) were selected as the most informative risk factors to classify patients according to their risk of adverse features, leading to the creation of five risk clusters. The adverse feature rates for cluster #1 (PI-RADS ≤3 and PSA density <0.15), cluster #2 (PI-RADS 4 and PSA density <0.15), cluster #3 (PI-RADS 1-4 and PSA density ≥0.15), cluster #4 (normal DRE [i.e., T1c] and PI-RADS 5), and cluster #5 (abnormal DRE [i.e., T2] and PI-RADS 5) were 11.8%, 27.9%, 37.3%, 42.7%, and 65.1%, respectively. Compared with the current EAU criteria, extending the AS criteria to clusters #1 and #2 or #1, #2, and #3 would increase the number of eligible patients (+60% and +253%, respectively) without increasing the risk of adverse pathological features. Conclusions: Pre-biopsy mpMRI plays a pivotal role in identifying the best IR candidates for AS. The newly developed model has the potential to expand the number of patients eligible for AS without compromising oncologic outcomes. Prospective studies investigating the oncologic safety of AS in IR patients using our model are needed to validate our findings. | F158: Eur. Urol. | G158: JOUR; Conference Abstract | H158: YES | I158: EXCLUDE | J158: Ineligible publication type | K158: CONFERENCE_ABSTRACT | L158: 46313 | M158: =IF(OR(I158="INCLUDE",I158="UNCERTAIN"),"RETRIEVE",IF(I158="EXCLUDE","EXCLUDE",""))
A159: 156 | B159: LIB-08372 | C159: 2024 | D159: Artificial intelligence and radiologists in prostate cancer detection on MRI (PI-CAI): an international, paired, noninferiority, confirmatory study | E159: Background Artificial intelligence (AI) systems can potentially aid the diagnostic pathway of prostate cancer by alleviating the increasing workload, preventing overdiagnosis, and reducing the dependence on experienced radiologists. We aimed to investigate the performance of AI systems at detecting clinically significant prostate cancer on MRI in comparison with radiologists using the Prostate Imaging-Reporting and Data System version 2.1 (PI-RADS 2.1) and the standard of care in multidisciplinary routine practice at scale. Methods In this international, paired, non -inferiority, confirmatory study, we trained and externally validated an AI system (developed within an international consortium) for detecting Gleason grade group 2 or greater cancers using a retrospective cohort of 10 207 MRI examinations from 9129 patients. Of these examinations, 9207 cases from three centres (11 sites) based in the Netherlands were used for training and tuning, and 1000 cases from four centres (12 sites) based in the Netherlands and Norway were used for testing. In parallel, we facilitated a multireader, multicase observer study with 62 radiologists (45 centres in 20 countries; median 7 [IQR 5-10] years of experience in reading prostate MRI) using PI-RADS (2.1) on 400 paired MRI examinations from the testing cohort. Primary endpoints were the sensitivity, specificity, and the area under the receiver operating characteristic curve (AUROC) of the AI system in comparison with that of all readers using PI-RADS (2.1) and in comparison with that of the historical radiology readings made during multidisciplinary routine practice (ie, the standard of care with the aid of patient history and peer consultation). Histopathology and at least 3 years (median 5 [IQR 4-6] years) of follow-up were used to establish the reference standard. The statistical analysis plan was prespecified with a primary hypothesis of noninferiority (considering a margin of 0<middle dot>05) and a secondary hypothesis of superiority towards the AI system, if noninferiority was confirmed. This study was registered at ClinicalTrials.gov, NCT05489341. Findings Of the 10 207 examinations included from Jan 1, 2012, through Dec 31, 2021, 2440 cases had histologically confirmed Gleason grade group 2 or greater prostate cancer. In the subset of 400 testing cases in which the AI system was compared with the radiologists participating in the reader study, the AI system showed a statistically superior and non-inferior AUROC of 0<middle dot>91 (95% CI 0<middle dot>87-0<middle dot>94; p<0<middle dot>0001), in comparison to the pool of 62 radiologists with an AUROC of 0<middle dot>86 (0<middle dot>83-0<middle dot>89), with a lower boundary of the two-sided 95% Wald CI for the difference in AUROC of 0<middle dot>02. At the mean PI-RADS 3 or greater operating point of all readers, the AI system detected 6 <middle dot> 8% more cases with Gleason grade group 2 or greater cancers at the same specificity (57 <middle dot> 7%, 95% CI 51<middle dot>6-63<middle dot>3), or 50 <middle dot> 4% fewer falsepositive results and 20 <middle dot> 0% fewer cases with Gleason grade group 1 cancers at the same sensitivity (89 <middle dot> 4%, 95% CI 85<middle dot>3-92<middle dot>9). In all 1000 testing cases where the AI system was compared with the radiology readings made during multidisciplinary practice, non -inferiority was not confirmed, as the AI system showed lower specificity (68<middle dot>9% [95% CI 65<middle dot>3-72<middle dot>4] vs 69 <middle dot> 0% [65 <middle dot> 5-72 <middle dot> 5]) at the same sensitivity (96<middle dot>1%, 94<middle dot>0-98<middle dot>2) as the PI-RADS 3 or greater operating point. The lower boundary of the two-sided 95% Wald CI for the difference in specificity (-0 <middle dot> 04) was greater than the non -inferiority margin (-0<middle dot>05) and a p value below the significance threshold was reached (p<0 <middle dot> 001). Interpretation An AI system was superior to radiologists using PI-RADS (2.1), on average, at detecting clinically significant prostate cancer and comparable to the standard of care. Such a system shows the potential to be a supportive tool within a primary diagnostic setting, with several associated benefits for patients and radiologists. Prospective validation is needed to test clinical applicability of this system. | F159: LANCET ONCOLOGY | G159: JOUR | H159: YES | I159: UNCERTAIN | K159: PI-CAI: AI vs radiologists/routine practice; verify retrospective vs prospective | L159: 46313 | M159: =IF(OR(I159="INCLUDE",I159="UNCERTAIN"),"RETRIEVE",IF(I159="EXCLUDE","EXCLUDE",""))
A160: 157 | B160: LIB-03987 | C160: 2026 | D160: On the current clinical applicability of artificial intelligence in pathology: An evidence-informed clinical readiness review. | E160: The integration of artificial intelligence (AI) into pathology practice is anticipated to drive substantial advancements. Numerous AI-based applications have been reported but the extent of their current clinical applicability remains uncertain. An evidence-informed clinical readiness review was conducted using the assistance of ChatGPT 5.1 Plus Thinking (OpenAI, San Francisco, CA). The initial summary provided by the large language model (LLM) was supplemented with additional data collected through further questioning and "conversation" between the authors and the LLM. The results were verified for accuracy and summarized by topic. The LLM provided useful outlines but extensive and time-consuming additional searches by the authors were needed to collect clinically relevant best evidence. Deep learning models (DLMs) for assistive diagnosis of prostate and breast cancer are being implemented in selected laboratories. DLMs for Pap smear assessment, metastasis detection, molecular inference, and other tasks have achieved promising results in curated settings but need further clinical validation. A variety of chatbots have been developed that show promise to enhance communications with patients and improve laboratory logistics. To date DLMs have shown great potential to improve the integration of clinico-pathologic data and can improve the diagnosis of selected entities. DLMs that can diagnose a more substantial number of pathological entities and provide better standardization of results reporting, prospective multicenter validation, and more detailed cost benefit analysis of AI-based models are needed prior to widespread adoption into the daily clinical practice of pathology. | F160: Annals of diagnostic pathology | G160: Journal Article; Review | H160: YES | I160: EXCLUDE | J160: Ineligible publication type | K160: NON_PRIMARY_PUBLICATION | L160: 46313 | M160: =IF(OR(I160="INCLUDE",I160="UNCERTAIN"),"RETRIEVE",IF(I160="EXCLUDE","EXCLUDE",""))
A161: 158 | B161: LIB-03149 | C161: 2024 | D161: Multiomics approach for patient stratification and novel target identification in metastatic clear cell renal carcinoma (Meet-URO 31) | E161: Background: The choice of the best treatment in first line metastatic clear-cell renal cell carcinoma (mccRCC) patients is becoming an issue, since no biomarkers are available to guide the treatment allocation strategy. Recently there has been a great deal of interest in Artificial Intelligence (AI) systems and their ability to process heterogeneous data for both classification and prediction purposes. An additional fields of interest in genitourinary oncology are also liquid biopsy and radiomics. Non-invasive liquid biopsy methods are able to detect and characterize circulating cell-free DNA (cfDNA), extracellular vesicles (EV) associated RNAs and circulating tumor cells (CTCs) and to allow longitudinal evaluation of tumor evolution whereas radiomics may provide a novel approach to develop predictive tools by correlating imaging features to tumor characteristics including histology, tumor grade, genetic patterns and molecular phenotypes, as well as clinical outcomes. We hypothesize that AI can be used to integrate data obtained from radiomics, genomic and transcriptomic analysis of CT scan, neoplastic tissues and circulating cell-free DNA or microvescicle-associated RNA with the purpose of defining an optimal allocation strategy for patients with mccRCC undergoing first-line therapy and identifying novel targets in mccRCC. Methods: This is a multicenter Italian prospective translational study evaluating transriptomic, genomics and radiomics in treatment-naïve advanced ccRCC patients. Subjects will be screened to identify a total of 100 patients eligible for the study, candidate to receive first-line treatment as per investigator’s choice according to clinical practice. Tumoral tissue, plasma samples and radiological exams will be collected at baseline, at 3 months, at the time of first radiological evaluation and at disease progression (PD) to provide a comprehensive molecular profile and radiomic features extrapolation, respectively. AI systems will be used to build a genomic-radiomic profile of patients to correlate to treatment response. The planned sample size of 100 patients will allow an exploratory analysis of the prognostic and predictive performance of the “multiomic” classifier, to be subsequently validated in a larger expansion cohort of patients. Through the above research we are confident to provide proof of concept that AI is able to combine the information from genomics, transcriptomic and radiomics to provide an opportunity for a molecularly driven patients’ stratification, aiming to choose the ideal first-line systemic treatment for each patient. Enrollment has already begun and the trial has enrolled 15 of the planned 100 patients. Clinical trial information: NCT05782400. Research Sponsor: AIRC (Italian Associacion for Cancer Research). © (2024), (Lippincott Williams and Wilkins). All rights reserved. | F161: Journal of Clinical Oncology | G161: JOUR; Article | H161: YES | I161: EXCLUDE | J161: Ineligible publication type | K161: CONFERENCE_ABSTRACT | L161: 46313 | M161: =IF(OR(I161="INCLUDE",I161="UNCERTAIN"),"RETRIEVE",IF(I161="EXCLUDE","EXCLUDE",""))
A162: 159 | B162: LIB-03613 | C162: 2026 | D162: A multi-paradigm evaluation spanning pixels to voxels for deep learning-based kidney tumor segmentation. | E162: Automated segmentation of kidney tumors from computed tomography (CT) scans is crit- ical for diagnosis, treatment planning, and monitoring of renal cell carcinoma (RCC). While recent deep learning models report high Dice scores (>0.97), their clinical utility remains questionable due to false positive predictions that misclassify healthy tissue as tumors and computational constraints limiting real-world deployment. Unlike existing studies that emphasise quantitative metrics, this work investigates the critical gap between high segmentation accuracy and clinical applicability. We systematically evaluate six diverse architectures spanning 2D CNNs (U-Net, MedSAM) to 3D volumetric models (nnU-Net, UNETR, Total Segmenta- tor, MIScnn) on the KiTS19 dataset, emphasising false positive analysis, boundary delineation accuracy, and computational feasibility. Key findings [1]: MONAI U-Net achieves Dice score of 0.98 but exhibits excessive false positives, undermining clinical trust [2]; nnU-Net provides balanced performance (Dice: 0.82) with consistent results but demands 16GB VRAM [3]; MedSAM achieves state-of-the-art accuracy (Dice: 0.99) with minimal false positives but re- quires high-end GPUs [4]; computational constraints prevented full training of UNETR. This study identifies that high Dice scores do not guarantee clinical utility and provides actionable insights for developing clinically feasible segmentation tools for renal oncology applications including treatment planning, longitudinal monitoring, and risk assessment. | F162: Journal of medical engineering & technology | G162: Journal Article | H162: YES | I162: EXCLUDE | J162: Technical-only/no downstream clinical task | K162: TECHNICAL_ONLY | L162: 46313 | M162: =IF(OR(I162="INCLUDE",I162="UNCERTAIN"),"RETRIEVE",IF(I162="EXCLUDE","EXCLUDE",""))
A163: 160 | B163: LIB-00638 | C163: 2021 | D163: Machine learning-based analysis of [18F]DCFPyL PET radiomics for risk stratification in primary prostate cancer. | E163: PURPOSE: Quantitative prostate-specific membrane antigen (PSMA) PET analysis may provide for non-invasive and objective risk stratification of primary prostate cancer (PCa) patients. We determined the ability of machine learning-based analysis of quantitative [18F]DCFPyL PET metrics to predict metastatic disease or high-risk pathological tumor features. METHODS: In a prospective cohort study, 76 patients with intermediate- to high-risk PCa scheduled for robot-assisted radical prostatectomy with extended pelvic lymph node dissection underwent pre-operative [18F]DCFPyL PET-CT. Primary tumors were delineated using 50-70% peak isocontour thresholds on images with and without partial-volume correction (PVC). Four hundred and eighty standardized radiomic features were extracted per tumor. Random forest models were trained to predict lymph node involvement (LNI), presence of any metastasis, Gleason score ≥ 8, and presence of extracapsular extension (ECE). For comparison, models were also trained using standard PET features (SUVs, volume, total PSMA uptake). Model performance was validated using 50 times repeated 5-fold cross-validation yielding the mean receiver-operator characteristic curve AUC. RESULTS: The radiomics-based machine learning models predicted LNI (AUC 0.86 ± 0.15, p < 0.01), nodal or distant metastasis (AUC 0.86 ± 0.14, p < 0.01), Gleason score (0.81 ± 0.16, p < 0.01), and ECE (0.76 ± 0.12, p < 0.01). The highest AUCs reached using standard PET metrics were lower than those of radiomics-based models. For LNI and metastasis prediction, PVC and a higher delineation threshold improved model stability. Machine learning pre-processing methods had a minor impact on model performance. CONCLUSION: Machine learning-based analysis of quantitative [18F]DCFPyL PET metrics can predict LNI and high-risk pathological tumor features in primary PCa patients. These findings indicate that PSMA expression detected on PET is related to both primary tumor histopathology and metastatic tendency. Multicenter external validation is needed to determine the benefits of using radiomics versus standard PET metrics in clinical practice. | F163: European journal of nuclear medicine and molecular imaging | G163: Journal Article; Multicenter Study | H163: YES | I163: EXCLUDE | J163: Retrospective-only/ineligible design | K163: RETROSPECTIVE_ONLY | L163: 46313 | M163: =IF(OR(I163="INCLUDE",I163="UNCERTAIN"),"RETRIEVE",IF(I163="EXCLUDE","EXCLUDE",""))
A164: 161 | B164: LIB-05630 | C164: 2024 | D164: Unfeasibility of common stochastic deep learning Methods for clinical decision support in the human- machine collaborative setting | E164: Purpose In recent years, the widespread integration of electronic health recordsin health-care systems led to increasing amounts of complexheterogeneous data in the medical sector, available for examination. While precision medicine could benefit from the vast amount of data in many ways, such as improved medical diagnosis and outcome prognosis, its volume exceeds human capacity for manual examina-tion. Data-driven techniques from the fields of statistics and machine learning (ML) are promising approaches for the exploitation of mentioned data. However, in contrast to many other domains, the adoption of machine-learning based techniques in critical application domains as the medical sector remains limited. Principal obstacles are the well-known shortcomings of ML based techniques, such as over-confident predictions on out-of-distribution data. Reliable estimates of predictive confidence of ML based predictions are indispensable for its integration into clinical decision support (CDS) applications, e.g., in human-machine collaborative scenarios. In these settings, many straightforward cases can be processed automatically by ML Methods , whereas medical professionals may assess cases which got marked as unreliable. In our work, we study the feasibility of common deep learning Methods for probabilistic inference in mentioned human- machine collaborative settings. For this study, we consider the specific use case of Prostate Cancer (PCa) mortality prediction which stands exemplary for applications in health care, where data-driven decision support solutions may be of great benefit for therapeutic outcome and economic assignment of medical resources. Methods The data used in this work was obtained from the Prostate, Lung, Colorectal, and Ovarian Cancer Screening Trial (PLCO), a large randomized and controlled US-based study aimed to determine the effects of screening on cancer-related mortality and secondary end-points. We selected a subset of the most expressive features using the Phik-correlation coefficient to detect non-linear dependencies. For our feasibility study of common deep learning Methods for probabilistic inference for clinical decision support, we wanted to quantify the reliability of its uncertainty estimates under data shift. Therefore, we distinguish between aleatoric uncertainty and epistemic uncertainty. While aleatoric uncertainty can be obtained by many common ML approaches, estimation of epistemic uncertainty requires more specific Methods , which can compare the chosen model function with others. We study two of the most common deep learning approaches able to capture epistemic uncertainty: Bayesian neural networks with mean field Gaussian priors and trivial neural network ensembles. Bayesian neural networks make use of the Bayesian approach, in which prior beliefs get updated by new observations, to define an approximate posterior distribution. Neural network ensembles com-bine several independently trained models to detect ambiguity in the learned model functions. To evaluate the model's inherent uncertainty estimates, we introduce sample-wise uncertainty measures for alea-toric and epistemic uncertainty, respectively. The so-called mean reversion property is imperative for some metrics to capture epistemic uncertainty. This property describes the model's behavior to revert to the prior belief in uncertain cases. ResultsThe deep learning models under study showed good capacity for PCa-related risk of death stratification, and we found the aleatoric uncer-tainty measures strongly correlated with the accuracy of the predictions. We demonstrate that the epistemic uncertainty measure slightly correlates with divergence from the training data. However, we find epistemic uncertainty is systematically underestimated with both Methods and only samples far away from the training data may reliably be distinguished. ConclusionWe showed that the evaluated Methods , Bayesian neural network and neural network ensembles, are not equipped for reliable detection of epistemic uncertainty in their predictions. Both techniques produce biased sampled functions and fail to sufficiently explore the posterior distribution. This means, albeit showing good results in in-distribution discrimination performance, the models are inadequate for applicationin clinical decision-making due to persisting overconfidence under data shift. Furthermore, the evaluated Methods would not benefit from a human-machine collaborative setting, as this would require acknowledging the limits of the evidence they possess. More advanced Methods are needed to bridge the gap for reliable CDS. | F164: Int. J. Comput. Assisted Radiol. Surg. | G164: JOUR; Conference Abstract | H164: YES | I164: EXCLUDE | J164: Ineligible publication type | K164: CONFERENCE_ABSTRACT | L164: 46313 | M164: =IF(OR(I164="INCLUDE",I164="UNCERTAIN"),"RETRIEVE",IF(I164="EXCLUDE","EXCLUDE",""))
A165: 162 | B165: LIB-03461 | C165: 2026 | D165: VALIDATION OF PROGRESS, A SIMPLE MACHINE-LEARNING DERIVED RISK STRATIFICATION SCORE FOR CASTRATION-RESISTANT PROSTATE CANCER | E165: Purpose: Castration-resistant prostate cancer (CRPC) is characterized by marked clinical heterogeneity and poor long-term survival, underscoring the need for tools that can rapidly and reliably individualize patient risk. While several prognostic models exist, their complexity has limited routine clinical use. Here, we developed and validated PROGRESS (PROstate cancer Global Risk Evaluation and Stratification Score), a simplified prognostic score, derived through machine learning-guided feature selection, to enhance risk stratification and support individualized, risk-informed clinical decision-making. Methods: PROGRESS was developed using baseline data from 2,035 metastatic CRPC patients enrolled in four different phase III trials. An unsupervised machine-learning approach was applied to identify latent patient subgroups with distinct survival outcomes irrespectively of allocated treatment arm, followed by classical multivariable modelling to derive a simple and straight-forward prognostic score based on routinely available objective laboratory variables. External validation was performed in three independent datasets comprising metastatic CRPC patients treated across different therapeutic settings (n=1,239) and non-metastatic CRPC patients managed with standard care (n=660). Overall survival was assessed using Kaplan-Meier and Cox regression analyses. Results: Unsupervised modelling identified two patient risk subpopulations with significantly different overall survival rates (median 27.4 vs 17.7 months; hazard ratio [HR] 2.20, 95% CI 1.91–2.54; p<.00001). Feature contribution analysis yielded three independent predictors -PSA, ALP, and AST- used to build PROGRESS. In the training cohort, PROGRESS demonstrated strong discrimination (AUC 0.89). Using a prespecified cut-off, patients classified as increased risk had significantly shorter survival than low-risk patients (median 18.3 vs 25.6 months; HR 1.72, 95% CI 1.50–1.97; p<.0001). PROGRESS prognostic performance was consistent across all validation cohorts, including metastatic and non-metastatic disease, with HRs ranging from 1.74 to 3.46 (all p<.0001). Conclusions: By integrating machine-learning-based pattern discovery with classical statistical modelling, PROGRESS provides a simple, objective, and clinically accessible approach for individual risk stratification in CRPC. Its reliance on three inexpensive, routinely measured laboratory parameters would facilitate practical implementation in clinical settings, enhancing visibility of underlying disease aggressiveness for individual clinical decision-making. PROGRESS could represent a pragmatic first step toward improving patient selection for clinical trials while identifying regulatory meaningful endpoints achievable in a sizeable patient population; further validation in prospective clinical studies and real-world datasets would allow to confirm its clinical utility and generalizability. PROGRESS can be freely accessed for research use only at the following link: https://dev.ai.topazium.com. | F165: medRxiv | G165: GEN; Preprint | H165: YES | I165: EXCLUDE | J165: Ineligible publication type | K165: PREPRINT_ONLY | L165: 46313 | M165: =IF(OR(I165="INCLUDE",I165="UNCERTAIN"),"RETRIEVE",IF(I165="EXCLUDE","EXCLUDE",""))
A166: 163 | B166: LIB-04068 | C166: 2026 | D166: Machine learning-derived mast cell-associated angiogenesis features can serve as prognostic targets for clear cell renal cell carcinoma. | E166: BACKGROUND: In clear cell renal cell carcinoma (ccRCC), mast cell activation and angiogenesis are crucial for disease progression, with interactions occurring between these processes. The involvement of mast cell-related angiogenic characteristics in ccRCC is not yet fully elucidated. To address this gap, this study aims to clarify the biological role and prognostic significance of mast cell-mediated angiogenesis in ccRCC, and to examine its links to the tumor microenvironment and disease progression. METHODS: We utilized bioinformatics techniques to integrate and analyze single-cell and bulk transcriptomics data. We developed prognostic models using ten classical machine learning algorithms and conducted intergroup differential gene extraction, functional pathway enrichment, immune infiltration, and somatic mutation analyses. Finally, the expression levels of the model genes were verified by quantitative real-time polymerase chain reaction (qRT-PCR). RESULTS: TNF-α signaling is significantly upregulated in mast cells within the ccRCC microenvironment, shaping an immunosuppressive microenvironment through receptor-ligand interactions such as SPP1-CD44 and CLEC2C-KLRB1. We developed a mast cell-associated angiogenesis score that demonstrates satisfactory accuracy in assessing prognosis for ccRCC patients. Patients in the high-risk group exhibited activation of oncogenic signaling pathways including JAK-STAT3, accompanied by immunosuppressive status and elevated genomic instability. Furthermore, we identified the core oncogene TIMP1 and the protective gene EMCN. CONCLUSIONS: Mast cell-associated angiogenesis features aid in prognostic assessment for ccRCC patients, with TIMP1 and EMCN representing potential therapeutic targets. | F166: Translational andrology and urology | G166: Journal Article | H166: YES | I166: EXCLUDE | J166: Retrospective-only/ineligible design | K166: RETROSPECTIVE_ONLY | L166: 46313 | M166: =IF(OR(I166="INCLUDE",I166="UNCERTAIN"),"RETRIEVE",IF(I166="EXCLUDE","EXCLUDE",""))
A167: 164 | B167: LIB-00655 | C167: 2021 | D167: Grading Evolution and Contemporary Prognostic Biomarkers of Clinically Significant Prostate Cancer. | E167: Gleason grading remains the strongest prognostic parameter in localized prostate adenocarcinoma. We have here outlined the evolution and contemporary practices in pathological evaluation of prostate tissue samples for Gleason score and Grade group. The state of more observer-independent grading methods with the aid of artificial intelligence is also reviewed. Additionally, we conducted a systematic review of biomarkers that hold promise in adding independent prognostic or predictive value on top of clinical parameters, Grade group and PSA. We especially focused on hard end points during the follow-up, i.e., occurrence of metastasis, disease-specific mortality and overall mortality. In peripheral blood, biopsy-detected prostate cancer or in surgical specimens, we can conclude that there are more than sixty biomarkers that have been shown to have independent prognostic significance when adjusted to conventional risk assessment or grouping. Our search brought up some known putative markers and panels, as expected. Also, the synthesis in the systematic review indicated markers that ought to be further studied as part of prospective trials and in well characterized patient cohorts in order to increase the resolution of the current clinico-pathological prognostic factors. | F167: Cancers | G167: Journal Article; Review | H167: YES | I167: EXCLUDE | J167: Ineligible publication type | K167: NON_PRIMARY_PUBLICATION | L167: 46313 | M167: =IF(OR(I167="INCLUDE",I167="UNCERTAIN"),"RETRIEVE",IF(I167="EXCLUDE","EXCLUDE",""))
A168: 165 | B168: LIB-04234 | C168: 2026 | D168: The Role of Artificial Intelligence in Optimizing Diagnosis in Prostate Cancer-A Narrative Review. | E168: Artificial intelligence (AI) is increasingly being investigated in prostate cancer (PCa) diagnosis and characterization, offering novel approaches to improve detection and risk stratification. This narrative review summarizes current evidence regarding the application of AI across the major stages of PCa management, with particular emphasis on radiomics and pathomics. Radiomics enables the extraction of high-dimensional quantitative features from medical imaging modalities, including ultrasound, computed tomography, multiparametric magnetic resonance imaging (mpMRI), and prostate-specific membrane antigen positron emission tomography (PSMA PET), providing imaging biomarkers that extend beyond conventional visual interpretation. Numerous studies have demonstrated that AI-based radiomic models improve the detection of clinically significant PCa, characterize tumor aggressiveness, predict extracapsular extension, and support individualized treatment selection. Among available imaging modalities, mpMRI remains the cornerstone for radiomics owing to its superior soft-tissue characterization, whereas PSMA PET radiomics has shown particular promise for assessing biologically aggressive disease and metastatic spread. Pathomics has further expanded the role of AI by enabling automated tumor detection, grading, quantification, and identification of adverse pathological features, with promising performance reported in selected retrospective validation studies. Despite encouraging results, widespread clinical implementation remains limited by heterogeneous imaging protocols, variability in data acquisition and annotation, lack of standardized workflows, insufficient prospective multicenter validation, and ethical and regulatory challenges. The aim of this review was to summarize current evidence on AI-based imaging analysis, radiomics, and pathomics for PCa detection, characterization, risk stratification, and pathological assessment, while highlighting the methodological challenges that currently limit clinical implementation. | F168: Journal of clinical medicine | G168: Journal Article; Review | H168: YES | I168: EXCLUDE | J168: Ineligible publication type | K168: NON_PRIMARY_PUBLICATION | L168: 46313 | M168: =IF(OR(I168="INCLUDE",I168="UNCERTAIN"),"RETRIEVE",IF(I168="EXCLUDE","EXCLUDE",""))
A169: 166 | B169: LIB-03639 | C169: 2026 | D169: Radiomics for the Prediction of Postoperative Chronic Kidney Disease in Renal Tumor Patients Undergoing Surgical Resection. | E169: INTRODUCTION: Chronic kidney disease (CKD) is a significant concern following renal tumor surgery, impacting long-term renal function and patient outcomes. This study investigated the potential of computed tomography (CT)-based radiomics as a quantitative imaging approach to predict postoperative CKD in kidney tumor patients. METHODS: We included adult patients with renal tumor surgery treated at our center between 2012 and 2022. Preoperative retrospective CT-imaging data were analyzed, and radiomic features were extracted from tumor lesions and renal parenchyma. Machine learning models were trained to predict postoperative new-onset CKD based on clinical information and radiomics. Model performance was assessed using five-fold cross-validation on the training set (n = 65) and on a separate test set (n = 17). Model performance was primarily evaluated using the receiver operating characteristic curve, with the area under the curve (AUC) serving as the principal summary metric. RESULTS: The study cohort comprised n = 82 patients, of whom n = 25 (30%) developed postoperative new-onset CKD. The best models achieved a mean validation AUC of 0.74 [95% CI: 0.60-0.86] for solely radiomics, 0.83 [0.73-0.93] with clinical information only, and 0.80 [0.67-0.91] on radiomics and clinical parameters, respectively (p > 0.05). For the test dataset, AUCs were 0.62 [95% CI: 0.29-0.92], 0.77 [0.50-0.98], and 0.80 [0.52-1.00], respectively (p > 0.05). CONCLUSION: Preoperative CT-based radiomic features in combination with clinical information can serve as a noninvasive predictor of postoperative CKD in renal tumor patients undergoing surgical resection. While prospective and external validation is needed, this approach facilitated clinical decision-making and enabled personalized treatment strategies in patients with renal tumors. | F169: Urologia internationalis | G169: Journal Article | H169: YES | I169: EXCLUDE | J169: Retrospective-only/ineligible design | K169: RETROSPECTIVE_ONLY | L169: 46313 | M169: =IF(OR(I169="INCLUDE",I169="UNCERTAIN"),"RETRIEVE",IF(I169="EXCLUDE","EXCLUDE",""))
A170: 167 | B170: LIB-01464 | C170: 2023 | D170: Enhancing Cancer Diagnosis with Real-Time Feedback: Tumor Metabolism through Hyperpolarized 1-13C Pyruvate MRSI. | E170: This review article discusses the potential of hyperpolarized (HP) 13C magnetic resonance spectroscopic imaging (MRSI) as a noninvasive technique for identifying altered metabolism in various cancer types. Hyperpolarization significantly improves the signal-to-noise ratio for the identification of 13C-labeled metabolites, enabling dynamic and real-time imaging of the conversion of [1-13C] pyruvate to [1-13C] lactate and/or [1-13C] alanine. The technique has shown promise in identifying upregulated glycolysis in most cancers, as compared to normal cells, and detecting successful treatment responses at an earlier stage than multiparametric MRI in breast and prostate cancer patients. The review provides a concise overview of the applications of HP [1-13C] pyruvate MRSI in various cancer systems, highlighting its potential for use in preclinical and clinical investigations, precision medicine, and long-term studies of therapeutic response. The article also discusses emerging frontiers in the field, such as combining multiple metabolic imaging techniques with HP MRSI for a more comprehensive view of cancer metabolism, and leveraging artificial intelligence to develop real-time, actionable biomarkers for early detection, assessing aggressiveness, and interrogating the early efficacy of therapies. | F170: Metabolites | G170: Journal Article; Review | H170: YES | I170: EXCLUDE | J170: Ineligible publication type | K170: NON_PRIMARY_PUBLICATION | L170: 46313 | M170: =IF(OR(I170="INCLUDE",I170="UNCERTAIN"),"RETRIEVE",IF(I170="EXCLUDE","EXCLUDE",""))
A171: 168 | B171: LIB-06443 | C171: 2023 | D171: Observer preference of artificial intelligence-generated versus clinical prostate contours for ultrasound-based high dose rate brachytherapy. | E171: BACKGROUND: For trans-rectal ultrasound (TRUS)-based high dose rate (HDR) prostate brachytherapy, prostate contouring can be challenging due to artifacts from implanted needles, bleeding, and calcifications. PURPOSE: To evaluate the geometric accuracy and observer preference of an artificial intelligence (AI) algorithm for generating prostate contours on TRUS images with implanted needles. METHODS: We conducted a retrospective study of 150 patients, who underwent HDR brachytherapy. These patients were randomly divided into training (104), validation (26) and testing (20) sets. An AI algorithm was trained/validated utilizing the TRUS image and reference (clinical) contours. The algorithm then provided contours for the test set. For evaluation, we calculated the Dice coefficient between AI and reference prostate contours. We then presented AI and reference contours to eight clinician observers, and asked observers to select their preference. Observers were blinded to the source of contours. We calculated the percentage of cases in which observers preferred AI contours. Lastly, we evaluate whether the presence of AI contours improved the geometric accuracy of prostate contours provided by five resident observers for a 10-patient subset. RESULTS: The median Dice coefficient between AI and reference contours was 0.92 (IQR: 0.90-0.94). Observers preferred AI contours for a median of 57.5% (IQR: 47.5, 65.0) of the test cases. For resident observers, the presence of AI contours was associated with a 0.107 (95% CI: 0.086, 0.128; p < 0.001) improvement in Dice coefficient for the 10-patient subset. CONCLUSION: The AI algorithm provided high-quality prostate contours on TRUS with implanted needles. Further prospective study is needed to better understand how to incorporate AI prostate contours into the TRUS-based HDR brachytherapy workflow. | F171: Medical physics | G171: Journal Article; Comparative Study | H171: YES | I171: EXCLUDE | J171: Retrospective-only/ineligible design | K171: RETROSPECTIVE_ONLY | L171: 46313 | M171: =IF(OR(I171="INCLUDE",I171="UNCERTAIN"),"RETRIEVE",IF(I171="EXCLUDE","EXCLUDE",""))
... A195: 192 | B195: LIB-04950 | C195: 2021 | D195: 68Ga-PSMA-11-PET/MRI radiomics in patients receiving 177Lu-617-PSMA-therapy | E195: Aim/Introduction: 177Lutetium PSMA-617 (Lu-PSMA) therapy is efficacious for the treatment of patients with metastasized castration-resistant prostate cancer (mCRPC) and has gained visibility through ongoing phase III trial. Prior to therapy 68Ga-PSMA-11-PET is used for evaluation of uptake. Data on prediction of therapy outcome and survival out of pretherapeutic imaging parameters is still sparse. In this study the predictive and prognostic value of radiomic imaging features from 68Ga-PSMA-11-PET/MRI are analyzed. Materials and Methods: 21 patients with mCRPC underwent 68Ga-PSMA-11-PET/MRI before Lu-PSMA therapy. PET positive volume was extracted and transferred to whole body T2-, T1- and contrast enhanced T1-weighted MR-sequences. Radiomic features from PET and MR-sequences were extracted by two independent readers. Stepwise reduction of radiomic features was performed and the balanced dataset was split into a training (70%) and a testing dataset (30%). Single and multiple logistic regression models were used for selecting variables that allow classification of biochemical response (PSA decrease >50%). For their correlation to overall survival (prognostic value) relevant parameters are tested. Results: Eight patients achieved biochemical response (PSA decline >50%) after a median of 3 cycles of Lu-PSMA therapy. Ten PET, T1 post Gd and T2 parameters differentiated well between responders and non-responders. Logistic regression model revealed highest accuracy (AUC = 0.83) for T2 interquartile range for the prediction of biochemical response after Lu-PSMA-therapy. Within the final model patients with biochemical response (p=0.003) and high T2 interquartile range (p=0.038) in pretherapeutic imaging survived significantly longer. Conclusion: This pilot study provides first evidence on a potential predicitve and prognostic value of 68Ga-PSMA-11-PET/MRI radiomics prior to Lu-PSMA therapy. Beyond imaging based parameters, blood based biomarkers and previous treatments should be included in future studies. | F195: Eur. J. Nucl. Med. Mol. Imaging | G195: JOUR; Conference Abstract | H195: YES | I195: EXCLUDE | J195: Ineligible publication type | K195: CONFERENCE_ABSTRACT | L195: 46313 | M195: =IF(OR(I195="INCLUDE",I195="UNCERTAIN"),"RETRIEVE",IF(I195="EXCLUDE","EXCLUDE",""))
A196: 193 | B196: LIB-04336 | C196: 2015 | D196: Human feasibility study of fluorescence spectroscopy guided optical biopsy needle for prostate cancer diagnosis. | E196: Current prostate biopsy cores have a very low diagnostic yield. These biopsies often fail to diagnose prostate cancer since 90% of cores are histopathologically classified as benign. The concentrations of endogenous fluorophores in prostate tissue vary with disease states. Thus, fluorescence spectroscopy could be utilized to quantify these variations for identification of malignant lesions. We investigated clinical feasibility of a 14 gauge (1.98 mm) optical biopsy needle guided by fluorescence spectroscopy for real-time in vivo prostate cancer diagnosis. Built-in optical sensor has 8×100μm fibers for tissue excitation and a single 200μm fiber to collect spectral data. Custom-made fluorometer has 2 light-emitting diodes at 290 and 340 nm and a spectrometer. User interface for fluorometer operation and data collection was developed using LabView software. Each spectral data acquisition required ~2 seconds. The in vivo biopsies were performed during radical retropubic prostatectomy surgery on the exposed prostate with blood flow to the gland intact. A tissue biopsy core was obtained from each biopsy site after acquisition of spectral data. Above procedure was repeated ex vivo after surgical excision of the prostate. Biopsy cores were histopathologically classified as either benign or malignant and correlated with corresponding spectral data. Partial Least Square analysis was performed to determine diagnostically significant principal components as potential classifiers. A linear support vector machine and leave-one-out cross validation method was employed for tissue classification. Thirteen patients were consented to the study. Histopathological analysis found cancer in 29/208 in vivo and 51/224 ex vivo viable biopsy cores. Study results show 72% sensitivity, 66% specificity, and 93% negative predictive value for in vivo and 75%, 80%, and 93%, respectively, for ex vivo malignant versus benign prostatic tissue classification. Optical biopsy needle has a very high negative predictive value to indicate benign tissue while sufficient sensitivity for targeting areas suspicious for cancer within the prostate gland. Hence, the optical biopsy needle can increase the diagnostic yield of prostate biopsies with consequent improvement in patient care. | F196: Annual International Conference of the IEEE Engineering in Medicine and Biology Society. IEEE Engineering in Medicine and Biology Society. Annual International Conference | G196: Journal Article; Research Support, Non-U.S. Gov't | H196: YES | I196: UNCERTAIN | K196: SVM on optical biopsy needle spectra, in vivo prospective feasibility | L196: 46313 | M196: =IF(OR(I196="INCLUDE",I196="UNCERTAIN"),"RETRIEVE",IF(I196="EXCLUDE","EXCLUDE",""))
A197: 194 | B197: LIB-06956 | C197: 2025 | D197: CINEPRO: Robust Training of Foundation Models for Cancer Detection in Prostate Ultrasound Cineloops | E197: Prostate cancer (PCa) detection using deep learning (DL) models has shown potential for enhancing real-time guidance during biopsies. However, prostate ultrasound images lack pixel-level cancer annotations, introducing label noise. Current approaches often focus on limited regions of interest (ROIs), disregarding anatomical context necessary for accurate diagnosis. Foundation models can overcome this limitation by analyzing entire images to capture global spatial relationships; however, they still encounter challenges stemming from the weak labels associated with coarse pathology annotations in ultrasound data. We introduce Cinepro, a novel framework that strengthens foundation models' ability to localize PCa in ultrasound cineloops. Cinepro adapts robust training by integrating the proportion of cancer tissue reported by pathology in a biopsy core into its loss function to address label noise, providing a more nuanced supervision. Additionally, it leverages temporal data across multiple frames to apply robust augmentations, enhancing the model's ability to learn stable cancer-related features. Cinepro demonstrates superior performance on a multi -center prostate ultrasound dataset, achieving an AUROC of 77.1 % and a balanced accuracy of 71.9%, surpassing current benchmarks. These findings underscore Cinepro's promise in advancing foundation models for weakly labeled ultrasound data. © 2025 IEEE. | F197: Proceedings - International Symposium on Biomedical Imaging | G197: CONF; Conference paper | H197: YES | I197: EXCLUDE | J197: Technical-only/no downstream clinical task | K197: TECHNICAL_ONLY | L197: 46313 | M197: =IF(OR(I197="INCLUDE",I197="UNCERTAIN"),"RETRIEVE",IF(I197="EXCLUDE","EXCLUDE",""))
